{
  "components": [
    {
      "Capabilities": {
        "PCFExternalServiceUsageAllowed": false
      },
      "ComponentName": "CustomControl",
      "Identifier": "msdyn_MscrmControls.Common.A11yFocusTrap",
      "IdentifierType": 0
    },
    {
      "Capabilities": {
        "PCFExternalServiceUsageAllowed": false
      },
      "ComponentName": "CustomControl",
      "Identifier": "msdyn_MscrmControls.Common.A11yFocusTrap",
      "IdentifierType": 0
    },
    {
      "Capabilities": {
        "PCFExternalServiceUsageAllowed": false
      },
      "ComponentName": "CustomControl",
      "Identifier": "msdyn_MscrmControls.Common.A11yFocusTrap",
      "IdentifierType": 0
    },
    {
      "Capabilities": {
        "PCFExternalServiceUsageAllowed": false
      },
      "ComponentName": "CustomControl",
      "Identifier": "msdyn_MscrmControls.Common.A11yFocusTrap",
      "IdentifierType": 0
    }
  ],
  "DatasetName": "default.cds",
  "EntityName": "Asset management released products storage dimension defaults (mserp)",
  "InstanceUrl": "https://aurorabapenv7cf94.crm10.dynamics.com/",
  "LocalReferenceDSJson": {
    "entitySetName": "mserp_entassetreleasedproductstoragedimensiondefaultsentities",
    "logicalName": "mserp_entassetreleasedproductstoragedimensiondefaultsentity"
  },
  "state": "Configured",
  "TableDefinition": {
    "BooleanOptionSetAttribute": "{\"@odata.context\":\"https://aurorabapenv7cf94.crm10.dynamics.com/api/data/v9.0/$metadata#EntityDefinitions('mserp_entassetreleasedproductstoragedimensiondefaultsentity')/Attributes/Microsoft.Dynamics.CRM.BooleanAttributeMetadata(MetadataId,LogicalName,SchemaName,DisplayName,OptionSet())\",\"value\":[]}",
    "DefaultPublicView": "{\"@odata.context\":\"https://aurorabapenv7cf94.crm10.dynamics.com/api/data/v9.0/$metadata#savedqueries(layoutxml)\",\"value\":[{\"@odata.etag\":\"W/\\\"7401016\\\"\",\"layoutxml\":\"<grid name=\\\"resultset\\\" object=\\\"11375\\\" jump=\\\"mserp_itemnumber\\\" select=\\\"1\\\" icon=\\\"1\\\" preview=\\\"1\\\"><row name=\\\"result\\\" id=\\\"mserp_entassetreleasedproductstoragedimensiondefaultsentityid\\\"><cell name=\\\"mserp_itemnumber\\\" width=\\\"300\\\" /></row></grid>\",\"savedqueryid\":\"65d365d1-aee0-cc5b-4002-4fa85c8aeadb\"}]}",
    "EntityMetadata": "{\"@odata.context\":\"https://aurorabapenv7cf94.crm10.dynamics.com/api/data/v9.0/$metadata#EntityDefinitions(MetadataId,LogicalName,DisplayCollectionName,EntitySetName,Description,HasNotes,IsActivity,IsIntersect,IsManaged,TableType,IsPrivate,IsLogicalEntity,PrimaryIdAttribute,PrimaryNameAttribute,ObjectTypeCode,OwnershipType,Privileges,IsAvailableOffline,IsOfflineInMobileClient,Attributes(),ManyToOneRelationships(),OneToManyRelationships(),ManyToManyRelationships())/$entity\",\"MetadataId\":\"8f5ae0d8-9ab4-ef11-a72f-6045bd0a486c\",\"IsActivity\":false,\"IsAvailableOffline\":false,\"IsIntersect\":false,\"IsManaged\":true,\"LogicalName\":\"mserp_entassetreleasedproductstoragedimensiondefaultsentity\",\"ObjectTypeCode\":11375,\"OwnershipType\":\"OrganizationOwned\",\"PrimaryNameAttribute\":\"mserp_itemnumber\",\"PrimaryIdAttribute\":\"mserp_entassetreleasedproductstoragedimensiondefaultsentityid\",\"EntitySetName\":\"mserp_entassetreleasedproductstoragedimensiondefaultsentities\",\"IsPrivate\":false,\"IsLogicalEntity\":false,\"HasNotes\":false,\"TableType\":\"Virtual\",\"Description\":{\"LocalizedLabels\":[],\"UserLocalizedLabel\":null},\"DisplayCollectionName\":{\"LocalizedLabels\":[{\"Label\":\"Asset management released products storage dimension defaults (mserp)\",\"LanguageCode\":1033,\"IsManaged\":true,\"MetadataId\":\"5b25f475-7dbf-432a-9247-5f672b324ef9\",\"HasChanged\":null}],\"UserLocalizedLabel\":{\"Label\":\"Asset management released products storage dimension defaults (mserp)\",\"LanguageCode\":1033,\"IsManaged\":true,\"MetadataId\":\"5b25f475-7dbf-432a-9247-5f672b324ef9\",\"HasChanged\":null}},\"IsOfflineInMobileClient\":{\"Value\":false,\"CanBeChanged\":true,\"ManagedPropertyLogicalName\":\"canmodifymobileclientoffline\"},\"Privileges\":[{\"CanBeBasic\":false,\"CanBeDeep\":false,\"CanBeGlobal\":true,\"CanBeLocal\":false,\"CanBeEntityReference\":false,\"CanBeParentEntityReference\":false,\"CanBeRecordFilter\":false,\"Name\":\"prvCreatemserp_entassetreleasedproductstoragedimensiondefaultsentity\",\"PrivilegeId\":\"72cb1fc1-e0be-4810-bf07-3f4206a12559\",\"PrivilegeType\":\"Create\"},{\"CanBeBasic\":false,\"CanBeDeep\":false,\"CanBeGlobal\":true,\"CanBeLocal\":false,\"CanBeEntityReference\":false,\"CanBeParentEntityReference\":false,\"CanBeRecordFilter\":false,\"Name\":\"prvReadmserp_entassetreleasedproductstoragedimensiondefaultsentity\",\"PrivilegeId\":\"5b8ab4c7-c551-4769-adf2-6ee183daea29\",\"PrivilegeType\":\"Read\"},{\"CanBeBasic\":false,\"CanBeDeep\":false,\"CanBeGlobal\":true,\"CanBeLocal\":false,\"CanBeEntityReference\":false,\"CanBeParentEntityReference\":false,\"CanBeRecordFilter\":false,\"Name\":\"prvWritemserp_entassetreleasedproductstoragedimensiondefaultsentity\",\"PrivilegeId\":\"9b4495ac-a9ef-4728-831a-bde2fe37bb2e\",\"PrivilegeType\":\"Write\"},{\"CanBeBasic\":false,\"CanBeDeep\":false,\"CanBeGlobal\":true,\"CanBeLocal\":false,\"CanBeEntityReference\":false,\"CanBeParentEntityReference\":false,\"CanBeRecordFilter\":false,\"Name\":\"prvDeletemserp_entassetreleasedproductstoragedimensiondefaultsentity\",\"PrivilegeId\":\"a621ee52-3d55-4326-ac34-d8c73c406f16\",\"PrivilegeType\":\"Delete\"},{\"CanBeBasic\":false,\"CanBeDeep\":false,\"CanBeGlobal\":true,\"CanBeLocal\":false,\"CanBeEntityReference\":false,\"CanBeParentEntityReference\":false,\"CanBeRecordFilter\":false,\"Name\":\"prvAppendmserp_entassetreleasedproductstoragedimensiondefaultsentity\",\"PrivilegeId\":\"4f1f28f8-e6a5-4bcb-9e95-0ec99bdae706\",\"PrivilegeType\":\"Append\"},{\"CanBeBasic\":false,\"CanBeDeep\":false,\"CanBeGlobal\":true,\"CanBeLocal\":false,\"CanBeEntityReference\":false,\"CanBeParentEntityReference\":false,\"CanBeRecordFilter\":false,\"Name\":\"prvAppendTomserp_entassetreleasedproductstoragedimensiondefaultsentity\",\"PrivilegeId\":\"b4077589-6f1c-4653-b907-1399077dcbe3\",\"PrivilegeType\":\"AppendTo\"}],\"Attributes\":[{\"@odata.type\":\"#Microsoft.Dynamics.CRM.StringAttributeMetadata\",\"MetadataId\":\"115be0d8-9ab4-ef11-a72f-6045bd0a486c\",\"HasChanged\":null,\"AttributeOf\":null,\"AttributeType\":\"String\",\"ColumnNumber\":12,\"DeprecatedVersion\":null,\"IntroducedVersion\":\"1.0.0.0\",\"EntityLogicalName\":\"mserp_entassetreleasedproductstoragedimensiondefaultsentity\",\"IsCustomAttribute\":true,\"IsPrimaryId\":false,\"IsValidODataAttribute\":true,\"IsPrimaryName\":false,\"IsValidForCreate\":true,\"IsValidForRead\":true,\"IsValidForUpdate\":true,\"CanBeSecuredForRead\":false,\"CanBeSecuredForCreate\":false,\"CanBeSecuredForUpdate\":false,\"IsSecured\":false,\"IsRetrievable\":false,\"IsFilterable\":false,\"IsSearchable\":false,\"IsManaged\":true,\"LinkedAttributeId\":null,\"LogicalName\":\"mserp_dataareaid\",\"IsValidForForm\":true,\"IsRequiredForForm\":false,\"IsValidForGrid\":true,\"SchemaName\":\"mserp_dataareaid\",\"ExternalName\":\"dataAreaId\",\"IsLogical\":false,\"IsDataSourceSecret\":false,\"InheritsFrom\":null,\"CreatedOn\":\"2024-12-07T12:57:48Z\",\"ModifiedOn\":\"2024-12-07T12:57:48Z\",\"SourceType\":0,\"AutoNumberFormat\":null,\"Format\":\"Text\",\"ImeMode\":\"Auto\",\"MaxLength\":4,\"YomiOf\":null,\"IsLocalizable\":false,\"DatabaseLength\":8,\"FormulaDefinition\":\"\",\"SourceTypeMask\":0,\"AttributeTypeName\":{\"Value\":\"StringType\"},\"Description\":{\"LocalizedLabels\":[],\"UserLocalizedLabel\":null},\"DisplayName\":{\"LocalizedLabels\":[{\"Label\":\"Company Code\",\"LanguageCode\":1033,\"IsManaged\":true,\"MetadataId\":\"0d84578d-7331-4085-90bd-330e951ae35f\",\"HasChanged\":null}],\"UserLocalizedLabel\":{\"Label\":\"Company Code\",\"LanguageCode\":1033,\"IsManaged\":true,\"MetadataId\":\"0d84578d-7331-4085-90bd-330e951ae35f\",\"HasChanged\":null}},\"IsAuditEnabled\":{\"Value\":true,\"CanBeChanged\":true,\"ManagedPropertyLogicalName\":\"canmodifyauditsettings\"},\"IsGlobalFilterEnabled\":{\"Value\":false,\"CanBeChanged\":true,\"ManagedPropertyLogicalName\":\"canmodifyglobalfiltersettings\"},\"IsSortableEnabled\":{\"Value\":false,\"CanBeChanged\":true,\"ManagedPropertyLogicalName\":\"canmodifyissortablesettings\"},\"IsCustomizable\":{\"Value\":false,\"CanBeChanged\":false,\"ManagedPropertyLogicalName\":\"iscustomizable\"},\"IsRenameable\":{\"Value\":true,\"CanBeChanged\":false,\"ManagedPropertyLogicalName\":\"isrenameable\"},\"IsValidForAdvancedFind\":{\"Value\":true,\"CanBeChanged\":true,\"ManagedPropertyLogicalName\":\"canmodifysearchsettings\"},\"RequiredLevel\":{\"Value\":\"Recommended\",\"CanBeChanged\":true,\"ManagedPropertyLogicalName\":\"canmodifyrequirementlevelsettings\"},\"CanModifyAdditionalSettings\":{\"Value\":true,\"CanBeChanged\":false,\"ManagedPropertyLogicalName\":\"canmodifyadditionalsettings\"},\"Settings\":[],\"FormatName\":{\"Value\":\"Text\"}},{\"@odata.type\":\"#Microsoft.Dynamics.CRM.LookupAttributeMetadata\",\"MetadataId\":\"2427a669-ae82-4af1-a960-88d5323333fd\",\"HasChanged\":null,\"AttributeOf\":null,\"AttributeType\":\"Lookup\",\"ColumnNumber\":13,\"DeprecatedVersion\":null,\"IntroducedVersion\":\"1.0.0.0\",\"EntityLogicalName\":\"mserp_entassetreleasedproductstoragedimensiondefaultsentity\",\"IsCustomAttribute\":true,\"IsPrimaryId\":false,\"IsValidODataAttribute\":true,\"IsPrimaryName\":false,\"IsValidForCreate\":true,\"IsValidForRead\":true,\"IsValidForUpdate\":true,\"CanBeSecuredForRead\":true,\"CanBeSecuredForCreate\":true,\"CanBeSecuredForUpdate\":true,\"IsSecured\":false,\"IsRetrievable\":false,\"IsFilterable\":false,\"IsSearchable\":false,\"IsManaged\":true,\"LinkedAttributeId\":null,\"LogicalName\":\"mserp_dataareaid_id\",\"IsValidForForm\":true,\"IsRequiredForForm\":false,\"IsValidForGrid\":true,\"SchemaName\":\"mserp_dataAreaId_id\",\"ExternalName\":\"dataAreaId\",\"IsLogical\":false,\"IsDataSourceSecret\":false,\"InheritsFrom\":null,\"CreatedOn\":\"2024-12-07T12:57:48Z\",\"ModifiedOn\":\"2024-12-07T12:57:48Z\",\"SourceType\":null,\"AutoNumberFormat\":null,\"Targets\":[\"cdm_company\"],\"Format\":\"None\",\"AttributeTypeName\":{\"Value\":\"LookupType\"},\"Description\":{\"LocalizedLabels\":[],\"UserLocalizedLabel\":null},\"DisplayName\":{\"LocalizedLabels\":[{\"Label\":\"Company\",\"LanguageCode\":1033,\"IsManaged\":true,\"MetadataId\":\"56d7c40e-c6ea-4091-8ee3-9e93c6b986b8\",\"HasChanged\":null}],\"UserLocalizedLabel\":{\"Label\":\"Company\",\"LanguageCode\":1033,\"IsManaged\":true,\"MetadataId\":\"56d7c40e-c6ea-4091-8ee3-9e93c6b986b8\",\"HasChanged\":null}},\"IsAuditEnabled\":{\"Value\":false,\"CanBeChanged\":true,\"ManagedPropertyLogicalName\":\"canmodifyauditsettings\"},\"IsGlobalFilterEnabled\":{\"Value\":false,\"CanBeChanged\":true,\"ManagedPropertyLogicalName\":\"canmodifyglobalfiltersettings\"},\"IsSortableEnabled\":{\"Value\":false,\"CanBeChanged\":true,\"ManagedPropertyLogicalName\":\"canmodifyissortablesettings\"},\"IsCustomizable\":{\"Value\":true,\"CanBeChanged\":false,\"ManagedPropertyLogicalName\":\"iscustomizable\"},\"IsRenameable\":{\"Value\":true,\"CanBeChanged\":false,\"ManagedPropertyLogicalName\":\"isrenameable\"},\"IsValidForAdvancedFind\":{\"Value\":true,\"CanBeChanged\":true,\"ManagedPropertyLogicalName\":\"canmodifysearchsettings\"},\"RequiredLevel\":{\"Value\":\"Recommended\",\"CanBeChanged\":true,\"ManagedPropertyLogicalName\":\"canmodifyrequirementlevelsettings\"},\"CanModifyAdditionalSettings\":{\"Value\":true,\"CanBeChanged\":false,\"ManagedPropertyLogicalName\":\"canmodifyadditionalsettings\"},\"Settings\":[]},{\"@odata.type\":\"#Microsoft.Dynamics.CRM.StringAttributeMetadata\",\"MetadataId\":\"00e6b37c-60b2-43eb-b1a4-2bfb9bb8901b\",\"HasChanged\":null,\"AttributeOf\":\"mserp_dataareaid_id\",\"AttributeType\":\"String\",\"ColumnNumber\":14,\"DeprecatedVersion\":null,\"IntroducedVersion\":\"1.0.0.0\",\"EntityLogicalName\":\"mserp_entassetreleasedproductstoragedimensiondefaultsentity\",\"IsCustomAttribute\":true,\"IsPrimaryId\":false,\"IsValidODataAttribute\":false,\"IsPrimaryName\":false,\"IsValidForCreate\":false,\"IsValidForRead\":true,\"IsValidForUpdate\":false,\"CanBeSecuredForRead\":false,\"CanBeSecuredForCreate\":false,\"CanBeSecuredForUpdate\":false,\"IsSecured\":false,\"IsRetrievable\":false,\"IsFilterable\":false,\"IsSearchable\":false,\"IsManaged\":false,\"LinkedAttributeId\":null,\"LogicalName\":\"mserp_dataareaid_idname\",\"IsValidForForm\":false,\"IsRequiredForForm\":false,\"IsValidForGrid\":false,\"SchemaName\":\"mserp_dataAreaId_idName\",\"ExternalName\":null,\"IsLogical\":true,\"IsDataSourceSecret\":false,\"InheritsFrom\":null,\"CreatedOn\":\"2024-12-07T12:57:48Z\",\"ModifiedOn\":\"2024-12-07T12:57:48Z\",\"SourceType\":0,\"AutoNumberFormat\":null,\"Format\":\"Text\",\"ImeMode\":\"Auto\",\"MaxLength\":20,\"YomiOf\":null,\"IsLocalizable\":false,\"DatabaseLength\":40,\"FormulaDefinition\":\"\",\"SourceTypeMask\":0,\"AttributeTypeName\":{\"Value\":\"StringType\"},\"Description\":{\"LocalizedLabels\":[],\"UserLocalizedLabel\":null},\"DisplayName\":{\"LocalizedLabels\":[],\"UserLocalizedLabel\":null},\"IsAuditEnabled\":{\"Value\":true,\"CanBeChanged\":true,\"ManagedPropertyLogicalName\":\"canmodifyauditsettings\"},\"IsGlobalFilterEnabled\":{\"Value\":false,\"CanBeChanged\":true,\"ManagedPropertyLogicalName\":\"canmodifyglobalfiltersettings\"},\"IsSortableEnabled\":{\"Value\":false,\"CanBeChanged\":true,\"ManagedPropertyLogicalName\":\"canmodifyissortablesettings\"},\"IsCustomizable\":{\"Value\":true,\"CanBeChanged\":true,\"ManagedPropertyLogicalName\":\"iscustomizable\"},\"IsRenameable\":{\"Value\":true,\"CanBeChanged\":true,\"ManagedPropertyLogicalName\":\"isrenameable\"},\"IsValidForAdvancedFind\":{\"Value\":false,\"CanBeChanged\":true,\"ManagedPropertyLogicalName\":\"canmodifysearchsettings\"},\"RequiredLevel\":{\"Value\":\"None\",\"CanBeChanged\":true,\"ManagedPropertyLogicalName\":\"canmodifyrequirementlevelsettings\"},\"CanModifyAdditionalSettings\":{\"Value\":true,\"CanBeChanged\":true,\"ManagedPropertyLogicalName\":\"canmodifyadditionalsettings\"},\"Settings\":[],\"FormatName\":{\"Value\":\"Text\"}},{\"MetadataId\":\"e742a913-0957-4a24-bc28-cb3d75676498\",\"HasChanged\":null,\"AttributeOf\":null,\"AttributeType\":\"Uniqueidentifier\",\"ColumnNumber\":1,\"DeprecatedVersion\":null,\"IntroducedVersion\":\"1.0.0.0\",\"EntityLogicalName\":\"mserp_entassetreleasedproductstoragedimensiondefaultsentity\",\"IsCustomAttribute\":false,\"IsPrimaryId\":true,\"IsValidODataAttribute\":true,\"IsPrimaryName\":false,\"IsValidForCreate\":true,\"IsValidForRead\":true,\"IsValidForUpdate\":false,\"CanBeSecuredForRead\":false,\"CanBeSecuredForCreate\":false,\"CanBeSecuredForUpdate\":false,\"IsSecured\":false,\"IsRetrievable\":true,\"IsFilterable\":true,\"IsSearchable\":false,\"IsManaged\":true,\"LinkedAttributeId\":null,\"LogicalName\":\"mserp_entassetreleasedproductstoragedimensiondefaultsentityid\",\"IsValidForForm\":false,\"IsRequiredForForm\":false,\"IsValidForGrid\":false,\"SchemaName\":\"mserp_entassetreleasedproductstoragedimensiondefaultsentityId\",\"ExternalName\":null,\"IsLogical\":false,\"IsDataSourceSecret\":false,\"InheritsFrom\":null,\"CreatedOn\":\"2024-12-07T12:57:45Z\",\"ModifiedOn\":\"2024-12-07T12:57:45Z\",\"SourceType\":null,\"AutoNumberFormat\":null,\"AttributeTypeName\":{\"Value\":\"UniqueidentifierType\"},\"Description\":{\"LocalizedLabels\":[{\"Label\":\"Unique identifier for entity instances\",\"LanguageCode\":1033,\"IsManaged\":true,\"MetadataId\":\"a25ae0d8-9ab4-ef11-a72f-6045bd0a486c\",\"HasChanged\":null}],\"UserLocalizedLabel\":{\"Label\":\"Unique identifier for entity instances\",\"LanguageCode\":1033,\"IsManaged\":true,\"MetadataId\":\"a25ae0d8-9ab4-ef11-a72f-6045bd0a486c\",\"HasChanged\":null}},\"DisplayName\":{\"LocalizedLabels\":[{\"Label\":\"Asset management released products storage dimension defaults (mserp)\",\"LanguageCode\":1033,\"IsManaged\":true,\"MetadataId\":\"a35ae0d8-9ab4-ef11-a72f-6045bd0a486c\",\"HasChanged\":null}],\"UserLocalizedLabel\":{\"Label\":\"Asset management released products storage dimension defaults (mserp)\",\"LanguageCode\":1033,\"IsManaged\":true,\"MetadataId\":\"a35ae0d8-9ab4-ef11-a72f-6045bd0a486c\",\"HasChanged\":null}},\"IsAuditEnabled\":{\"Value\":false,\"CanBeChanged\":false,\"ManagedPropertyLogicalName\":\"canmodifyauditsettings\"},\"IsGlobalFilterEnabled\":{\"Value\":false,\"CanBeChanged\":true,\"ManagedPropertyLogicalName\":\"canmodifyglobalfiltersettings\"},\"IsSortableEnabled\":{\"Value\":false,\"CanBeChanged\":true,\"ManagedPropertyLogicalName\":\"canmodifyissortablesettings\"},\"IsCustomizable\":{\"Value\":true,\"CanBeChanged\":false,\"ManagedPropertyLogicalName\":\"iscustomizable\"},\"IsRenameable\":{\"Value\":true,\"CanBeChanged\":false,\"ManagedPropertyLogicalName\":\"isrenameable\"},\"IsValidForAdvancedFind\":{\"Value\":true,\"CanBeChanged\":true,\"ManagedPropertyLogicalName\":\"canmodifysearchsettings\"},\"RequiredLevel\":{\"Value\":\"SystemRequired\",\"CanBeChanged\":false,\"ManagedPropertyLogicalName\":\"canmodifyrequirementlevelsettings\"},\"CanModifyAdditionalSettings\":{\"Value\":true,\"CanBeChanged\":false,\"ManagedPropertyLogicalName\":\"canmodifyadditionalsettings\"},\"Settings\":[]},{\"@odata.type\":\"#Microsoft.Dynamics.CRM.PicklistAttributeMetadata\",\"MetadataId\":\"0e5be0d8-9ab4-ef11-a72f-6045bd0a486c\",\"HasChanged\":null,\"AttributeOf\":null,\"AttributeType\":\"Picklist\",\"ColumnNumber\":10,\"DeprecatedVersion\":null,\"IntroducedVersion\":\"1.0.0.0\",\"EntityLogicalName\":\"mserp_entassetreleasedproductstoragedimensiondefaultsentity\",\"IsCustomAttribute\":true,\"IsPrimaryId\":false,\"IsValidODataAttribute\":true,\"IsPrimaryName\":false,\"IsValidForCreate\":true,\"IsValidForRead\":true,\"IsValidForUpdate\":true,\"CanBeSecuredForRead\":false,\"CanBeSecuredForCreate\":false,\"CanBeSecuredForUpdate\":false,\"IsSecured\":false,\"IsRetrievable\":false,\"IsFilterable\":false,\"IsSearchable\":false,\"IsManaged\":true,\"LinkedAttributeId\":null,\"LogicalName\":\"mserp_isadvancedwarehouseenabled\",\"IsValidForForm\":true,\"IsRequiredForForm\":false,\"IsValidForGrid\":true,\"SchemaName\":\"mserp_isadvancedwarehouseenabled\",\"ExternalName\":\"IsAdvancedWarehouseEnabled\",\"IsLogical\":false,\"IsDataSourceSecret\":false,\"InheritsFrom\":null,\"CreatedOn\":\"2024-12-07T12:57:47Z\",\"ModifiedOn\":\"2024-12-07T12:57:47Z\",\"SourceType\":0,\"AutoNumberFormat\":null,\"DefaultFormValue\":null,\"FormulaDefinition\":\"\",\"SourceTypeMask\":0,\"ParentPicklistLogicalName\":null,\"ChildPicklistLogicalNames\":[],\"AttributeTypeName\":{\"Value\":\"PicklistType\"},\"Description\":{\"LocalizedLabels\":[],\"UserLocalizedLabel\":null},\"DisplayName\":{\"LocalizedLabels\":[{\"Label\":\"Use warehouse management processes\",\"LanguageCode\":1033,\"IsManaged\":true,\"MetadataId\":\"e2dec8d4-ab31-44b1-b4e4-ec008038d905\",\"HasChanged\":null}],\"UserLocalizedLabel\":{\"Label\":\"Use warehouse management processes\",\"LanguageCode\":1033,\"IsManaged\":true,\"MetadataId\":\"e2dec8d4-ab31-44b1-b4e4-ec008038d905\",\"HasChanged\":null}},\"IsAuditEnabled\":{\"Value\":true,\"CanBeChanged\":true,\"ManagedPropertyLogicalName\":\"canmodifyauditsettings\"},\"IsGlobalFilterEnabled\":{\"Value\":false,\"CanBeChanged\":true,\"ManagedPropertyLogicalName\":\"canmodifyglobalfiltersettings\"},\"IsSortableEnabled\":{\"Value\":false,\"CanBeChanged\":true,\"ManagedPropertyLogicalName\":\"canmodifyissortablesettings\"},\"IsCustomizable\":{\"Value\":true,\"CanBeChanged\":false,\"ManagedPropertyLogicalName\":\"iscustomizable\"},\"IsRenameable\":{\"Value\":true,\"CanBeChanged\":false,\"ManagedPropertyLogicalName\":\"isrenameable\"},\"IsValidForAdvancedFind\":{\"Value\":true,\"CanBeChanged\":true,\"ManagedPropertyLogicalName\":\"canmodifysearchsettings\"},\"RequiredLevel\":{\"Value\":\"None\",\"CanBeChanged\":true,\"ManagedPropertyLogicalName\":\"canmodifyrequirementlevelsettings\"},\"CanModifyAdditionalSettings\":{\"Value\":false,\"CanBeChanged\":false,\"ManagedPropertyLogicalName\":\"canmodifyadditionalsettings\"},\"Settings\":[]},{\"MetadataId\":\"5000e82e-726d-4309-af28-0580e449f3b6\",\"HasChanged\":null,\"AttributeOf\":\"mserp_isadvancedwarehouseenabled\",\"AttributeType\":\"Virtual\",\"ColumnNumber\":11,\"DeprecatedVersion\":null,\"IntroducedVersion\":\"1.0.0.0\",\"EntityLogicalName\":\"mserp_entassetreleasedproductstoragedimensiondefaultsentity\",\"IsCustomAttribute\":true,\"IsPrimaryId\":false,\"IsValidODataAttribute\":false,\"IsPrimaryName\":false,\"IsValidForCreate\":false,\"IsValidForRead\":true,\"IsValidForUpdate\":false,\"CanBeSecuredForRead\":false,\"CanBeSecuredForCreate\":false,\"CanBeSecuredForUpdate\":false,\"IsSecured\":false,\"IsRetrievable\":false,\"IsFilterable\":false,\"IsSearchable\":false,\"IsManaged\":false,\"LinkedAttributeId\":null,\"LogicalName\":\"mserp_isadvancedwarehouseenabledname\",\"IsValidForForm\":false,\"IsRequiredForForm\":false,\"IsValidForGrid\":false,\"SchemaName\":\"mserp_isadvancedwarehouseenabledName\",\"ExternalName\":null,\"IsLogical\":true,\"IsDataSourceSecret\":false,\"InheritsFrom\":null,\"CreatedOn\":\"2024-12-07T12:57:47Z\",\"ModifiedOn\":\"2024-12-07T12:57:47Z\",\"SourceType\":null,\"AutoNumberFormat\":null,\"AttributeTypeName\":{\"Value\":\"VirtualType\"},\"Description\":{\"LocalizedLabels\":[],\"UserLocalizedLabel\":null},\"DisplayName\":{\"LocalizedLabels\":[],\"UserLocalizedLabel\":null},\"IsAuditEnabled\":{\"Value\":false,\"CanBeChanged\":true,\"ManagedPropertyLogicalName\":\"canmodifyauditsettings\"},\"IsGlobalFilterEnabled\":{\"Value\":false,\"CanBeChanged\":true,\"ManagedPropertyLogicalName\":\"canmodifyglobalfiltersettings\"},\"IsSortableEnabled\":{\"Value\":false,\"CanBeChanged\":true,\"ManagedPropertyLogicalName\":\"canmodifyissortablesettings\"},\"IsCustomizable\":{\"Value\":true,\"CanBeChanged\":true,\"ManagedPropertyLogicalName\":\"iscustomizable\"},\"IsRenameable\":{\"Value\":true,\"CanBeChanged\":true,\"ManagedPropertyLogicalName\":\"isrenameable\"},\"IsValidForAdvancedFind\":{\"Value\":false,\"CanBeChanged\":true,\"ManagedPropertyLogicalName\":\"canmodifysearchsettings\"},\"RequiredLevel\":{\"Value\":\"None\",\"CanBeChanged\":true,\"ManagedPropertyLogicalName\":\"canmodifyrequirementlevelsettings\"},\"CanModifyAdditionalSettings\":{\"Value\":true,\"CanBeChanged\":true,\"ManagedPropertyLogicalName\":\"canmodifyadditionalsettings\"},\"Settings\":[]},{\"@odata.type\":\"#Microsoft.Dynamics.CRM.PicklistAttributeMetadata\",\"MetadataId\":\"0b5be0d8-9ab4-ef11-a72f-6045bd0a486c\",\"HasChanged\":null,\"AttributeOf\":null,\"AttributeType\":\"Picklist\",\"ColumnNumber\":8,\"DeprecatedVersion\":null,\"IntroducedVersion\":\"1.0.0.0\",\"EntityLogicalName\":\"mserp_entassetreleasedproductstoragedimensiondefaultsentity\",\"IsCustomAttribute\":true,\"IsPrimaryId\":false,\"IsValidODataAttribute\":true,\"IsPrimaryName\":false,\"IsValidForCreate\":true,\"IsValidForRead\":true,\"IsValidForUpdate\":true,\"CanBeSecuredForRead\":false,\"CanBeSecuredForCreate\":false,\"CanBeSecuredForUpdate\":false,\"IsSecured\":false,\"IsRetrievable\":false,\"IsFilterable\":false,\"IsSearchable\":false,\"IsManaged\":true,\"LinkedAttributeId\":null,\"LogicalName\":\"mserp_iswarehouselocationdimensionactive\",\"IsValidForForm\":true,\"IsRequiredForForm\":false,\"IsValidForGrid\":true,\"SchemaName\":\"mserp_iswarehouselocationdimensionactive\",\"ExternalName\":\"IsWarehouseLocationDimensionActive\",\"IsLogical\":false,\"IsDataSourceSecret\":false,\"InheritsFrom\":null,\"CreatedOn\":\"2024-12-07T12:57:47Z\",\"ModifiedOn\":\"2024-12-07T12:57:47Z\",\"SourceType\":0,\"AutoNumberFormat\":null,\"DefaultFormValue\":null,\"FormulaDefinition\":\"\",\"SourceTypeMask\":0,\"ParentPicklistLogicalName\":null,\"ChildPicklistLogicalNames\":[],\"AttributeTypeName\":{\"Value\":\"PicklistType\"},\"Description\":{\"LocalizedLabels\":[],\"UserLocalizedLabel\":null},\"DisplayName\":{\"LocalizedLabels\":[{\"Label\":\"Active\",\"LanguageCode\":1033,\"IsManaged\":true,\"MetadataId\":\"659b1fb5-2be8-41f6-b4d0-d7b1b2baee04\",\"HasChanged\":null}],\"UserLocalizedLabel\":{\"Label\":\"Active\",\"LanguageCode\":1033,\"IsManaged\":true,\"MetadataId\":\"659b1fb5-2be8-41f6-b4d0-d7b1b2baee04\",\"HasChanged\":null}},\"IsAuditEnabled\":{\"Value\":true,\"CanBeChanged\":true,\"ManagedPropertyLogicalName\":\"canmodifyauditsettings\"},\"IsGlobalFilterEnabled\":{\"Value\":false,\"CanBeChanged\":true,\"ManagedPropertyLogicalName\":\"canmodifyglobalfiltersettings\"},\"IsSortableEnabled\":{\"Value\":false,\"CanBeChanged\":true,\"ManagedPropertyLogicalName\":\"canmodifyissortablesettings\"},\"IsCustomizable\":{\"Value\":true,\"CanBeChanged\":false,\"ManagedPropertyLogicalName\":\"iscustomizable\"},\"IsRenameable\":{\"Value\":true,\"CanBeChanged\":false,\"ManagedPropertyLogicalName\":\"isrenameable\"},\"IsValidForAdvancedFind\":{\"Value\":true,\"CanBeChanged\":true,\"ManagedPropertyLogicalName\":\"canmodifysearchsettings\"},\"RequiredLevel\":{\"Value\":\"None\",\"CanBeChanged\":true,\"ManagedPropertyLogicalName\":\"canmodifyrequirementlevelsettings\"},\"CanModifyAdditionalSettings\":{\"Value\":false,\"CanBeChanged\":false,\"ManagedPropertyLogicalName\":\"canmodifyadditionalsettings\"},\"Settings\":[]},{\"MetadataId\":\"9e6dbcfe-1894-49be-a30b-7470c61f81ca\",\"HasChanged\":null,\"AttributeOf\":\"mserp_iswarehouselocationdimensionactive\",\"AttributeType\":\"Virtual\",\"ColumnNumber\":9,\"DeprecatedVersion\":null,\"IntroducedVersion\":\"1.0.0.0\",\"EntityLogicalName\":\"mserp_entassetreleasedproductstoragedimensiondefaultsentity\",\"IsCustomAttribute\":true,\"IsPrimaryId\":false,\"IsValidODataAttribute\":false,\"IsPrimaryName\":false,\"IsValidForCreate\":false,\"IsValidForRead\":true,\"IsValidForUpdate\":false,\"CanBeSecuredForRead\":false,\"CanBeSecuredForCreate\":false,\"CanBeSecuredForUpdate\":false,\"IsSecured\":false,\"IsRetrievable\":false,\"IsFilterable\":false,\"IsSearchable\":false,\"IsManaged\":false,\"LinkedAttributeId\":null,\"LogicalName\":\"mserp_iswarehouselocationdimensionactivename\",\"IsValidForForm\":false,\"IsRequiredForForm\":false,\"IsValidForGrid\":false,\"SchemaName\":\"mserp_iswarehouselocationdimensionactiveName\",\"ExternalName\":null,\"IsLogical\":true,\"IsDataSourceSecret\":false,\"InheritsFrom\":null,\"CreatedOn\":\"2024-12-07T12:57:47Z\",\"ModifiedOn\":\"2024-12-07T12:57:47Z\",\"SourceType\":null,\"AutoNumberFormat\":null,\"AttributeTypeName\":{\"Value\":\"VirtualType\"},\"Description\":{\"LocalizedLabels\":[],\"UserLocalizedLabel\":null},\"DisplayName\":{\"LocalizedLabels\":[],\"UserLocalizedLabel\":null},\"IsAuditEnabled\":{\"Value\":false,\"CanBeChanged\":true,\"ManagedPropertyLogicalName\":\"canmodifyauditsettings\"},\"IsGlobalFilterEnabled\":{\"Value\":false,\"CanBeChanged\":true,\"ManagedPropertyLogicalName\":\"canmodifyglobalfiltersettings\"},\"IsSortableEnabled\":{\"Value\":false,\"CanBeChanged\":true,\"ManagedPropertyLogicalName\":\"canmodifyissortablesettings\"},\"IsCustomizable\":{\"Value\":true,\"CanBeChanged\":true,\"ManagedPropertyLogicalName\":\"iscustomizable\"},\"IsRenameable\":{\"Value\":true,\"CanBeChanged\":true,\"ManagedPropertyLogicalName\":\"isrenameable\"},\"IsValidForAdvancedFind\":{\"Value\":false,\"CanBeChanged\":true,\"ManagedPropertyLogicalName\":\"canmodifysearchsettings\"},\"RequiredLevel\":{\"Value\":\"None\",\"CanBeChanged\":true,\"ManagedPropertyLogicalName\":\"canmodifyrequirementlevelsettings\"},\"CanModifyAdditionalSettings\":{\"Value\":true,\"CanBeChanged\":true,\"ManagedPropertyLogicalName\":\"canmodifyadditionalsettings\"},\"Settings\":[]},{\"@odata.type\":\"#Microsoft.Dynamics.CRM.StringAttributeMetadata\",\"MetadataId\":\"905ae0d8-9ab4-ef11-a72f-6045bd0a486c\",\"HasChanged\":null,\"AttributeOf\":null,\"AttributeType\":\"String\",\"ColumnNumber\":2,\"DeprecatedVersion\":null,\"IntroducedVersion\":\"1.0.0.0\",\"EntityLogicalName\":\"mserp_entassetreleasedproductstoragedimensiondefaultsentity\",\"IsCustomAttribute\":true,\"IsPrimaryId\":false,\"IsValidODataAttribute\":true,\"IsPrimaryName\":true,\"IsValidForCreate\":true,\"IsValidForRead\":true,\"IsValidForUpdate\":true,\"CanBeSecuredForRead\":false,\"CanBeSecuredForCreate\":false,\"CanBeSecuredForUpdate\":false,\"IsSecured\":false,\"IsRetrievable\":true,\"IsFilterable\":false,\"IsSearchable\":true,\"IsManaged\":true,\"LinkedAttributeId\":null,\"LogicalName\":\"mserp_itemnumber\",\"IsValidForForm\":true,\"IsRequiredForForm\":true,\"IsValidForGrid\":true,\"SchemaName\":\"mserp_itemnumber\",\"ExternalName\":\"ItemNumber\",\"IsLogical\":false,\"IsDataSourceSecret\":false,\"InheritsFrom\":null,\"CreatedOn\":\"2024-12-07T12:57:45Z\",\"ModifiedOn\":\"2024-12-07T12:57:45Z\",\"SourceType\":0,\"AutoNumberFormat\":null,\"Format\":\"Text\",\"ImeMode\":\"Auto\",\"MaxLength\":20,\"YomiOf\":null,\"IsLocalizable\":false,\"DatabaseLength\":40,\"FormulaDefinition\":\"\",\"SourceTypeMask\":0,\"AttributeTypeName\":{\"Value\":\"StringType\"},\"Description\":{\"LocalizedLabels\":[],\"UserLocalizedLabel\":null},\"DisplayName\":{\"LocalizedLabels\":[{\"Label\":\"Item number\",\"LanguageCode\":1033,\"IsManaged\":true,\"MetadataId\":\"8ecb8efa-a12f-4b6b-a161-df28d0ba2f4a\",\"HasChanged\":null}],\"UserLocalizedLabel\":{\"Label\":\"Item number\",\"LanguageCode\":1033,\"IsManaged\":true,\"MetadataId\":\"8ecb8efa-a12f-4b6b-a161-df28d0ba2f4a\",\"HasChanged\":null}},\"IsAuditEnabled\":{\"Value\":true,\"CanBeChanged\":true,\"ManagedPropertyLogicalName\":\"canmodifyauditsettings\"},\"IsGlobalFilterEnabled\":{\"Value\":false,\"CanBeChanged\":true,\"ManagedPropertyLogicalName\":\"canmodifyglobalfiltersettings\"},\"IsSortableEnabled\":{\"Value\":false,\"CanBeChanged\":true,\"ManagedPropertyLogicalName\":\"canmodifyissortablesettings\"},\"IsCustomizable\":{\"Value\":true,\"CanBeChanged\":false,\"ManagedPropertyLogicalName\":\"iscustomizable\"},\"IsRenameable\":{\"Value\":true,\"CanBeChanged\":false,\"ManagedPropertyLogicalName\":\"isrenameable\"},\"IsValidForAdvancedFind\":{\"Value\":true,\"CanBeChanged\":true,\"ManagedPropertyLogicalName\":\"canmodifysearchsettings\"},\"RequiredLevel\":{\"Value\":\"ApplicationRequired\",\"CanBeChanged\":true,\"ManagedPropertyLogicalName\":\"canmodifyrequirementlevelsettings\"},\"CanModifyAdditionalSettings\":{\"Value\":true,\"CanBeChanged\":false,\"ManagedPropertyLogicalName\":\"canmodifyadditionalsettings\"},\"Settings\":[],\"FormatName\":{\"Value\":\"Text\"}},{\"@odata.type\":\"#Microsoft.Dynamics.CRM.StringAttributeMetadata\",\"MetadataId\":\"935ae0d8-9ab4-ef11-a72f-6045bd0a486c\",\"HasChanged\":null,\"AttributeOf\":null,\"AttributeType\":\"String\",\"ColumnNumber\":5,\"DeprecatedVersion\":null,\"IntroducedVersion\":\"1.0.0.0\",\"EntityLogicalName\":\"mserp_entassetreleasedproductstoragedimensiondefaultsentity\",\"IsCustomAttribute\":true,\"IsPrimaryId\":false,\"IsValidODataAttribute\":true,\"IsPrimaryName\":false,\"IsValidForCreate\":false,\"IsValidForRead\":true,\"IsValidForUpdate\":false,\"CanBeSecuredForRead\":false,\"CanBeSecuredForCreate\":false,\"CanBeSecuredForUpdate\":false,\"IsSecured\":false,\"IsRetrievable\":false,\"IsFilterable\":false,\"IsSearchable\":false,\"IsManaged\":true,\"LinkedAttributeId\":null,\"LogicalName\":\"mserp_productdefaultsiteid\",\"IsValidForForm\":true,\"IsRequiredForForm\":false,\"IsValidForGrid\":true,\"SchemaName\":\"mserp_productdefaultsiteid\",\"ExternalName\":\"ProductDefaultSiteId\",\"IsLogical\":false,\"IsDataSourceSecret\":false,\"InheritsFrom\":null,\"CreatedOn\":\"2024-12-07T12:57:45Z\",\"ModifiedOn\":\"2024-12-07T12:57:45Z\",\"SourceType\":0,\"AutoNumberFormat\":null,\"Format\":\"Text\",\"ImeMode\":\"Auto\",\"MaxLength\":10,\"YomiOf\":null,\"IsLocalizable\":false,\"DatabaseLength\":20,\"FormulaDefinition\":\"\",\"SourceTypeMask\":0,\"AttributeTypeName\":{\"Value\":\"StringType\"},\"Description\":{\"LocalizedLabels\":[],\"UserLocalizedLabel\":null},\"DisplayName\":{\"LocalizedLabels\":[{\"Label\":\"Site\",\"LanguageCode\":1033,\"IsManaged\":true,\"MetadataId\":\"71172acf-07ef-48bb-9578-a62c750a731c\",\"HasChanged\":null}],\"UserLocalizedLabel\":{\"Label\":\"Site\",\"LanguageCode\":1033,\"IsManaged\":true,\"MetadataId\":\"71172acf-07ef-48bb-9578-a62c750a731c\",\"HasChanged\":null}},\"IsAuditEnabled\":{\"Value\":true,\"CanBeChanged\":true,\"ManagedPropertyLogicalName\":\"canmodifyauditsettings\"},\"IsGlobalFilterEnabled\":{\"Value\":false,\"CanBeChanged\":true,\"ManagedPropertyLogicalName\":\"canmodifyglobalfiltersettings\"},\"IsSortableEnabled\":{\"Value\":false,\"CanBeChanged\":true,\"ManagedPropertyLogicalName\":\"canmodifyissortablesettings\"},\"IsCustomizable\":{\"Value\":true,\"CanBeChanged\":false,\"ManagedPropertyLogicalName\":\"iscustomizable\"},\"IsRenameable\":{\"Value\":true,\"CanBeChanged\":false,\"ManagedPropertyLogicalName\":\"isrenameable\"},\"IsValidForAdvancedFind\":{\"Value\":true,\"CanBeChanged\":true,\"ManagedPropertyLogicalName\":\"canmodifysearchsettings\"},\"RequiredLevel\":{\"Value\":\"None\",\"CanBeChanged\":true,\"ManagedPropertyLogicalName\":\"canmodifyrequirementlevelsettings\"},\"CanModifyAdditionalSettings\":{\"Value\":false,\"CanBeChanged\":false,\"ManagedPropertyLogicalName\":\"canmodifyadditionalsettings\"},\"Settings\":[],\"FormatName\":{\"Value\":\"Text\"}},{\"@odata.type\":\"#Microsoft.Dynamics.CRM.StringAttributeMetadata\",\"MetadataId\":\"945ae0d8-9ab4-ef11-a72f-6045bd0a486c\",\"HasChanged\":null,\"AttributeOf\":null,\"AttributeType\":\"String\",\"ColumnNumber\":6,\"DeprecatedVersion\":null,\"IntroducedVersion\":\"1.0.0.0\",\"EntityLogicalName\":\"mserp_entassetreleasedproductstoragedimensiondefaultsentity\",\"IsCustomAttribute\":true,\"IsPrimaryId\":false,\"IsValidODataAttribute\":true,\"IsPrimaryName\":false,\"IsValidForCreate\":false,\"IsValidForRead\":true,\"IsValidForUpdate\":false,\"CanBeSecuredForRead\":false,\"CanBeSecuredForCreate\":false,\"CanBeSecuredForUpdate\":false,\"IsSecured\":false,\"IsRetrievable\":false,\"IsFilterable\":false,\"IsSearchable\":false,\"IsManaged\":true,\"LinkedAttributeId\":null,\"LogicalName\":\"mserp_productdefaultwarehouseid\",\"IsValidForForm\":true,\"IsRequiredForForm\":false,\"IsValidForGrid\":true,\"SchemaName\":\"mserp_productdefaultwarehouseid\",\"ExternalName\":\"ProductDefaultWarehouseId\",\"IsLogical\":false,\"IsDataSourceSecret\":false,\"InheritsFrom\":null,\"CreatedOn\":\"2024-12-07T12:57:45Z\",\"ModifiedOn\":\"2024-12-07T12:57:45Z\",\"SourceType\":0,\"AutoNumberFormat\":null,\"Format\":\"Text\",\"ImeMode\":\"Auto\",\"MaxLength\":10,\"YomiOf\":null,\"IsLocalizable\":false,\"DatabaseLength\":20,\"FormulaDefinition\":\"\",\"SourceTypeMask\":0,\"AttributeTypeName\":{\"Value\":\"StringType\"},\"Description\":{\"LocalizedLabels\":[],\"UserLocalizedLabel\":null},\"DisplayName\":{\"LocalizedLabels\":[{\"Label\":\"Warehouse\",\"LanguageCode\":1033,\"IsManaged\":true,\"MetadataId\":\"345ed7c6-5a8d-4580-ba54-dbbd79c88b9c\",\"HasChanged\":null}],\"UserLocalizedLabel\":{\"Label\":\"Warehouse\",\"LanguageCode\":1033,\"IsManaged\":true,\"MetadataId\":\"345ed7c6-5a8d-4580-ba54-dbbd79c88b9c\",\"HasChanged\":null}},\"IsAuditEnabled\":{\"Value\":true,\"CanBeChanged\":true,\"ManagedPropertyLogicalName\":\"canmodifyauditsettings\"},\"IsGlobalFilterEnabled\":{\"Value\":false,\"CanBeChanged\":true,\"ManagedPropertyLogicalName\":\"canmodifyglobalfiltersettings\"},\"IsSortableEnabled\":{\"Value\":false,\"CanBeChanged\":true,\"ManagedPropertyLogicalName\":\"canmodifyissortablesettings\"},\"IsCustomizable\":{\"Value\":true,\"CanBeChanged\":false,\"ManagedPropertyLogicalName\":\"iscustomizable\"},\"IsRenameable\":{\"Value\":true,\"CanBeChanged\":false,\"ManagedPropertyLogicalName\":\"isrenameable\"},\"IsValidForAdvancedFind\":{\"Value\":true,\"CanBeChanged\":true,\"ManagedPropertyLogicalName\":\"canmodifysearchsettings\"},\"RequiredLevel\":{\"Value\":\"None\",\"CanBeChanged\":true,\"ManagedPropertyLogicalName\":\"canmodifyrequirementlevelsettings\"},\"CanModifyAdditionalSettings\":{\"Value\":false,\"CanBeChanged\":false,\"ManagedPropertyLogicalName\":\"canmodifyadditionalsettings\"},\"Settings\":[],\"FormatName\":{\"Value\":\"Text\"}},{\"@odata.type\":\"#Microsoft.Dynamics.CRM.StringAttributeMetadata\",\"MetadataId\":\"955ae0d8-9ab4-ef11-a72f-6045bd0a486c\",\"HasChanged\":null,\"AttributeOf\":null,\"AttributeType\":\"String\",\"ColumnNumber\":7,\"DeprecatedVersion\":null,\"IntroducedVersion\":\"1.0.0.0\",\"EntityLogicalName\":\"mserp_entassetreleasedproductstoragedimensiondefaultsentity\",\"IsCustomAttribute\":true,\"IsPrimaryId\":false,\"IsValidODataAttribute\":true,\"IsPrimaryName\":false,\"IsValidForCreate\":false,\"IsValidForRead\":true,\"IsValidForUpdate\":false,\"CanBeSecuredForRead\":false,\"CanBeSecuredForCreate\":false,\"CanBeSecuredForUpdate\":false,\"IsSecured\":false,\"IsRetrievable\":false,\"IsFilterable\":false,\"IsSearchable\":false,\"IsManaged\":true,\"LinkedAttributeId\":null,\"LogicalName\":\"mserp_productdefaultwarehouselocationid\",\"IsValidForForm\":true,\"IsRequiredForForm\":false,\"IsValidForGrid\":true,\"SchemaName\":\"mserp_productdefaultwarehouselocationid\",\"ExternalName\":\"ProductDefaultWarehouseLocationId\",\"IsLogical\":false,\"IsDataSourceSecret\":false,\"InheritsFrom\":null,\"CreatedOn\":\"2024-12-07T12:57:45Z\",\"ModifiedOn\":\"2024-12-07T12:57:45Z\",\"SourceType\":0,\"AutoNumberFormat\":null,\"Format\":\"Text\",\"ImeMode\":\"Auto\",\"MaxLength\":10,\"YomiOf\":null,\"IsLocalizable\":false,\"DatabaseLength\":20,\"FormulaDefinition\":\"\",\"SourceTypeMask\":0,\"AttributeTypeName\":{\"Value\":\"StringType\"},\"Description\":{\"LocalizedLabels\":[],\"UserLocalizedLabel\":null},\"DisplayName\":{\"LocalizedLabels\":[{\"Label\":\"Location\",\"LanguageCode\":1033,\"IsManaged\":true,\"MetadataId\":\"1216f131-8b6d-4dbd-9cd1-740764fdad6a\",\"HasChanged\":null}],\"UserLocalizedLabel\":{\"Label\":\"Location\",\"LanguageCode\":1033,\"IsManaged\":true,\"MetadataId\":\"1216f131-8b6d-4dbd-9cd1-740764fdad6a\",\"HasChanged\":null}},\"IsAuditEnabled\":{\"Value\":true,\"CanBeChanged\":true,\"ManagedPropertyLogicalName\":\"canmodifyauditsettings\"},\"IsGlobalFilterEnabled\":{\"Value\":false,\"CanBeChanged\":true,\"ManagedPropertyLogicalName\":\"canmodifyglobalfiltersettings\"},\"IsSortableEnabled\":{\"Value\":false,\"CanBeChanged\":true,\"ManagedPropertyLogicalName\":\"canmodifyissortablesettings\"},\"IsCustomizable\":{\"Value\":true,\"CanBeChanged\":false,\"ManagedPropertyLogicalName\":\"iscustomizable\"},\"IsRenameable\":{\"Value\":true,\"CanBeChanged\":false,\"ManagedPropertyLogicalName\":\"isrenameable\"},\"IsValidForAdvancedFind\":{\"Value\":true,\"CanBeChanged\":true,\"ManagedPropertyLogicalName\":\"canmodifysearchsettings\"},\"RequiredLevel\":{\"Value\":\"None\",\"CanBeChanged\":true,\"ManagedPropertyLogicalName\":\"canmodifyrequirementlevelsettings\"},\"CanModifyAdditionalSettings\":{\"Value\":false,\"CanBeChanged\":false,\"ManagedPropertyLogicalName\":\"canmodifyadditionalsettings\"},\"Settings\":[],\"FormatName\":{\"Value\":\"Text\"}},{\"@odata.type\":\"#Microsoft.Dynamics.CRM.StringAttributeMetadata\",\"MetadataId\":\"915ae0d8-9ab4-ef11-a72f-6045bd0a486c\",\"HasChanged\":null,\"AttributeOf\":null,\"AttributeType\":\"String\",\"ColumnNumber\":3,\"DeprecatedVersion\":null,\"IntroducedVersion\":\"1.0.0.0\",\"EntityLogicalName\":\"mserp_entassetreleasedproductstoragedimensiondefaultsentity\",\"IsCustomAttribute\":true,\"IsPrimaryId\":false,\"IsValidODataAttribute\":true,\"IsPrimaryName\":false,\"IsValidForCreate\":true,\"IsValidForRead\":true,\"IsValidForUpdate\":true,\"CanBeSecuredForRead\":false,\"CanBeSecuredForCreate\":false,\"CanBeSecuredForUpdate\":false,\"IsSecured\":false,\"IsRetrievable\":false,\"IsFilterable\":false,\"IsSearchable\":false,\"IsManaged\":true,\"LinkedAttributeId\":null,\"LogicalName\":\"mserp_searchname\",\"IsValidForForm\":true,\"IsRequiredForForm\":false,\"IsValidForGrid\":true,\"SchemaName\":\"mserp_searchname\",\"ExternalName\":\"SearchName\",\"IsLogical\":false,\"IsDataSourceSecret\":false,\"InheritsFrom\":null,\"CreatedOn\":\"2024-12-07T12:57:45Z\",\"ModifiedOn\":\"2024-12-07T12:57:45Z\",\"SourceType\":0,\"AutoNumberFormat\":null,\"Format\":\"Text\",\"ImeMode\":\"Auto\",\"MaxLength\":20,\"YomiOf\":null,\"IsLocalizable\":false,\"DatabaseLength\":40,\"FormulaDefinition\":\"\",\"SourceTypeMask\":0,\"AttributeTypeName\":{\"Value\":\"StringType\"},\"Description\":{\"LocalizedLabels\":[],\"UserLocalizedLabel\":null},\"DisplayName\":{\"LocalizedLabels\":[{\"Label\":\"Search name\",\"LanguageCode\":1033,\"IsManaged\":true,\"MetadataId\":\"c8e610fd-a1bd-403a-a54e-5e14d8df53e0\",\"HasChanged\":null}],\"UserLocalizedLabel\":{\"Label\":\"Search name\",\"LanguageCode\":1033,\"IsManaged\":true,\"MetadataId\":\"c8e610fd-a1bd-403a-a54e-5e14d8df53e0\",\"HasChanged\":null}},\"IsAuditEnabled\":{\"Value\":true,\"CanBeChanged\":true,\"ManagedPropertyLogicalName\":\"canmodifyauditsettings\"},\"IsGlobalFilterEnabled\":{\"Value\":false,\"CanBeChanged\":true,\"ManagedPropertyLogicalName\":\"canmodifyglobalfiltersettings\"},\"IsSortableEnabled\":{\"Value\":false,\"CanBeChanged\":true,\"ManagedPropertyLogicalName\":\"canmodifyissortablesettings\"},\"IsCustomizable\":{\"Value\":true,\"CanBeChanged\":false,\"ManagedPropertyLogicalName\":\"iscustomizable\"},\"IsRenameable\":{\"Value\":true,\"CanBeChanged\":false,\"ManagedPropertyLogicalName\":\"isrenameable\"},\"IsValidForAdvancedFind\":{\"Value\":true,\"CanBeChanged\":true,\"ManagedPropertyLogicalName\":\"canmodifysearchsettings\"},\"RequiredLevel\":{\"Value\":\"None\",\"CanBeChanged\":true,\"ManagedPropertyLogicalName\":\"canmodifyrequirementlevelsettings\"},\"CanModifyAdditionalSettings\":{\"Value\":false,\"CanBeChanged\":false,\"ManagedPropertyLogicalName\":\"canmodifyadditionalsettings\"},\"Settings\":[],\"FormatName\":{\"Value\":\"Text\"}},{\"@odata.type\":\"#Microsoft.Dynamics.CRM.StringAttributeMetadata\",\"MetadataId\":\"925ae0d8-9ab4-ef11-a72f-6045bd0a486c\",\"HasChanged\":null,\"AttributeOf\":null,\"AttributeType\":\"String\",\"ColumnNumber\":4,\"DeprecatedVersion\":null,\"IntroducedVersion\":\"1.0.0.0\",\"EntityLogicalName\":\"mserp_entassetreleasedproductstoragedimensiondefaultsentity\",\"IsCustomAttribute\":true,\"IsPrimaryId\":false,\"IsValidODataAttribute\":true,\"IsPrimaryName\":false,\"IsValidForCreate\":true,\"IsValidForRead\":true,\"IsValidForUpdate\":false,\"CanBeSecuredForRead\":false,\"CanBeSecuredForCreate\":false,\"CanBeSecuredForUpdate\":false,\"IsSecured\":false,\"IsRetrievable\":false,\"IsFilterable\":false,\"IsSearchable\":false,\"IsManaged\":true,\"LinkedAttributeId\":null,\"LogicalName\":\"mserp_storagedimensiongroupname\",\"IsValidForForm\":true,\"IsRequiredForForm\":false,\"IsValidForGrid\":true,\"SchemaName\":\"mserp_storagedimensiongroupname\",\"ExternalName\":\"StorageDimensionGroupName\",\"IsLogical\":false,\"IsDataSourceSecret\":false,\"InheritsFrom\":null,\"CreatedOn\":\"2024-12-07T12:57:45Z\",\"ModifiedOn\":\"2024-12-07T12:57:45Z\",\"SourceType\":0,\"AutoNumberFormat\":null,\"Format\":\"Text\",\"ImeMode\":\"Auto\",\"MaxLength\":10,\"YomiOf\":null,\"IsLocalizable\":false,\"DatabaseLength\":20,\"FormulaDefinition\":\"\",\"SourceTypeMask\":0,\"AttributeTypeName\":{\"Value\":\"StringType\"},\"Description\":{\"LocalizedLabels\":[],\"UserLocalizedLabel\":null},\"DisplayName\":{\"LocalizedLabels\":[{\"Label\":\"Storage dimension group\",\"LanguageCode\":1033,\"IsManaged\":true,\"MetadataId\":\"394e25c5-a0c3-41bd-ad12-f2a2dcc3a068\",\"HasChanged\":null}],\"UserLocalizedLabel\":{\"Label\":\"Storage dimension group\",\"LanguageCode\":1033,\"IsManaged\":true,\"MetadataId\":\"394e25c5-a0c3-41bd-ad12-f2a2dcc3a068\",\"HasChanged\":null}},\"IsAuditEnabled\":{\"Value\":true,\"CanBeChanged\":true,\"ManagedPropertyLogicalName\":\"canmodifyauditsettings\"},\"IsGlobalFilterEnabled\":{\"Value\":false,\"CanBeChanged\":true,\"ManagedPropertyLogicalName\":\"canmodifyglobalfiltersettings\"},\"IsSortableEnabled\":{\"Value\":false,\"CanBeChanged\":true,\"ManagedPropertyLogicalName\":\"canmodifyissortablesettings\"},\"IsCustomizable\":{\"Value\":true,\"CanBeChanged\":false,\"ManagedPropertyLogicalName\":\"iscustomizable\"},\"IsRenameable\":{\"Value\":true,\"CanBeChanged\":false,\"ManagedPropertyLogicalName\":\"isrenameable\"},\"IsValidForAdvancedFind\":{\"Value\":true,\"CanBeChanged\":true,\"ManagedPropertyLogicalName\":\"canmodifysearchsettings\"},\"RequiredLevel\":{\"Value\":\"None\",\"CanBeChanged\":true,\"ManagedPropertyLogicalName\":\"canmodifyrequirementlevelsettings\"},\"CanModifyAdditionalSettings\":{\"Value\":false,\"CanBeChanged\":false,\"ManagedPropertyLogicalName\":\"canmodifyadditionalsettings\"},\"Settings\":[],\"FormatName\":{\"Value\":\"Text\"}}],\"ManyToOneRelationships\":[{\"MetadataId\":\"155be0d8-9ab4-ef11-a72f-6045bd0a486c\",\"HasChanged\":null,\"IsCustomRelationship\":true,\"IsValidForAdvancedFind\":true,\"SchemaName\":\"mserp_EntAssetReleasedProductStorageDimensionDefaultsEntity_dataAreaId_rel\",\"SecurityTypes\":\"Append\",\"IsManaged\":true,\"RelationshipType\":\"OneToManyRelationship\",\"IntroducedVersion\":\"1.0.0.0\",\"ReferencedAttribute\":\"cdm_companyid\",\"ReferencedEntity\":\"cdm_company\",\"ReferencingAttribute\":\"mserp_dataareaid_id\",\"ReferencingEntity\":\"mserp_entassetreleasedproductstoragedimensiondefaultsentity\",\"IsHierarchical\":false,\"EntityKey\":null,\"IsRelationshipAttributeDenormalized\":false,\"ReferencedEntityNavigationPropertyName\":\"mserp_EntAssetReleasedProductStorageDimensionDefaultsEntity_dataAreaId_rel\",\"ReferencingEntityNavigationPropertyName\":\"mserp_dataAreaId_id\",\"RelationshipBehavior\":1,\"IsDenormalizedLookup\":null,\"DenormalizedAttributeName\":null,\"IsCustomizable\":{\"Value\":true,\"CanBeChanged\":false,\"ManagedPropertyLogicalName\":\"iscustomizable\"},\"AssociatedMenuConfiguration\":{\"Behavior\":\"UseCollectionName\",\"Group\":\"Details\",\"Order\":10000,\"IsCustomizable\":true,\"Icon\":null,\"ViewId\":\"00000000-0000-0000-0000-000000000000\",\"AvailableOffline\":true,\"MenuId\":null,\"QueryApi\":null,\"Label\":{\"LocalizedLabels\":[],\"UserLocalizedLabel\":null}},\"CascadeConfiguration\":{\"Assign\":\"NoCascade\",\"Delete\":\"NoCascade\",\"Archive\":\"RemoveLink\",\"Merge\":\"NoCascade\",\"Reparent\":\"NoCascade\",\"Share\":\"NoCascade\",\"Unshare\":\"NoCascade\",\"RollupView\":\"NoCascade\"},\"RelationshipAttributes\":[]}],\"OneToManyRelationships\":[],\"ManyToManyRelationships\":[]}",
    "EntityNameOptionSetAttribute": "{\"@odata.context\":\"https://aurorabapenv7cf94.crm10.dynamics.com/api/data/v9.0/$metadata#EntityDefinitions('mserp_entassetreleasedproductstoragedimensiondefaultsentity')/Attributes/Microsoft.Dynamics.CRM.EntityNameAttributeMetadata(MetadataId,LogicalName,SchemaName,DisplayName,OptionSet())\",\"value\":[]}",
    "Forms": "{\"@odata.context\":\"https://aurorabapenv7cf94.crm10.dynamics.com/api/data/v9.0/$metadata#systemforms(name,formid)\",\"value\":[{\"@odata.etag\":\"W/\\\"7400957\\\"\",\"objecttypecode\":\"mserp_entassetreleasedproductstoragedimensiondefaultsentity\",\"formid\":\"c76b129d-910f-33fc-d500-7693406076aa\",\"name\":\"Information\",\"type\":6},{\"@odata.etag\":\"W/\\\"7400932\\\"\",\"objecttypecode\":\"mserp_entassetreleasedproductstoragedimensiondefaultsentity\",\"formid\":\"0415a612-d651-ec15-5ccf-a283d3429ef2\",\"name\":\"Information\",\"type\":11},{\"@odata.etag\":\"W/\\\"7400886\\\"\",\"objecttypecode\":\"mserp_entassetreleasedproductstoragedimensiondefaultsentity\",\"formid\":\"21bce157-5ed3-5ce5-be13-ef3f2f18bbcc\",\"name\":\"Information\",\"type\":2}]}",
    "IconUrl": "",
    "MultiSelectPicklistOptionSetAttribute": "{\"@odata.context\":\"https://aurorabapenv7cf94.crm10.dynamics.com/api/data/v9.0/$metadata#EntityDefinitions('mserp_entassetreleasedproductstoragedimensiondefaultsentity')/Attributes/Microsoft.Dynamics.CRM.MultiSelectPicklistAttributeMetadata(MetadataId,LogicalName,SchemaName,DisplayName,OptionSet())\",\"value\":[]}",
    "PicklistOptionSetAttribute": "{\"@odata.context\":\"https://aurorabapenv7cf94.crm10.dynamics.com/api/data/v9.0/$metadata#EntityDefinitions('mserp_entassetreleasedproductstoragedimensiondefaultsentity')/Attributes/Microsoft.Dynamics.CRM.PicklistAttributeMetadata(MetadataId,LogicalName,SchemaName,DisplayName,OptionSet())\",\"value\":[{\"@odata.type\":\"#Microsoft.Dynamics.CRM.PicklistAttributeMetadata\",\"MetadataId\":\"0e5be0d8-9ab4-ef11-a72f-6045bd0a486c\",\"LogicalName\":\"mserp_isadvancedwarehouseenabled\",\"SchemaName\":\"mserp_isadvancedwarehouseenabled\",\"DisplayName\":{\"LocalizedLabels\":[{\"Label\":\"Use warehouse management processes\",\"LanguageCode\":1033,\"IsManaged\":true,\"MetadataId\":\"e2dec8d4-ab31-44b1-b4e4-ec008038d905\",\"HasChanged\":null}],\"UserLocalizedLabel\":{\"Label\":\"Use warehouse management processes\",\"LanguageCode\":1033,\"IsManaged\":true,\"MetadataId\":\"e2dec8d4-ab31-44b1-b4e4-ec008038d905\",\"HasChanged\":null}},\"OptionSet\":{\"MetadataId\":\"d4e2dc39-7db4-ef11-a72f-6045bd0a486c\",\"HasChanged\":null,\"IsCustomOptionSet\":true,\"IsGlobal\":true,\"IsManaged\":true,\"Name\":\"mserp_noyes\",\"ExternalTypeName\":\"NoYes\",\"OptionSetType\":\"Picklist\",\"IntroducedVersion\":\"1.0.0.0\",\"ParentOptionSetName\":null,\"Description\":{\"LocalizedLabels\":[],\"UserLocalizedLabel\":null},\"DisplayName\":{\"LocalizedLabels\":[{\"Label\":\"NoYes (mserp)\",\"LanguageCode\":1033,\"IsManaged\":true,\"MetadataId\":\"d5e2dc39-7db4-ef11-a72f-6045bd0a486c\",\"HasChanged\":null}],\"UserLocalizedLabel\":{\"Label\":\"NoYes (mserp)\",\"LanguageCode\":1033,\"IsManaged\":true,\"MetadataId\":\"d5e2dc39-7db4-ef11-a72f-6045bd0a486c\",\"HasChanged\":null}},\"IsCustomizable\":{\"Value\":true,\"CanBeChanged\":false,\"ManagedPropertyLogicalName\":\"iscustomizable\"},\"Options\":[{\"Value\":200000000,\"Color\":null,\"IsManaged\":true,\"ExternalValue\":\"No\",\"ParentValues\":[],\"Tag\":null,\"IsHidden\":false,\"MetadataId\":null,\"HasChanged\":null,\"Label\":{\"LocalizedLabels\":[{\"Label\":\"No\",\"LanguageCode\":1033,\"IsManaged\":true,\"MetadataId\":\"4738e8e9-d095-4f43-a072-34abcb3039bc\",\"HasChanged\":null}],\"UserLocalizedLabel\":{\"Label\":\"No\",\"LanguageCode\":1033,\"IsManaged\":true,\"MetadataId\":\"4738e8e9-d095-4f43-a072-34abcb3039bc\",\"HasChanged\":null}},\"Description\":{\"LocalizedLabels\":[],\"UserLocalizedLabel\":null}},{\"Value\":200000001,\"Color\":null,\"IsManaged\":true,\"ExternalValue\":\"Yes\",\"ParentValues\":[],\"Tag\":null,\"IsHidden\":false,\"MetadataId\":null,\"HasChanged\":null,\"Label\":{\"LocalizedLabels\":[{\"Label\":\"Yes\",\"LanguageCode\":1033,\"IsManaged\":true,\"MetadataId\":\"032d13c5-c04d-41ef-b5ed-4784639ac7fc\",\"HasChanged\":null}],\"UserLocalizedLabel\":{\"Label\":\"Yes\",\"LanguageCode\":1033,\"IsManaged\":true,\"MetadataId\":\"032d13c5-c04d-41ef-b5ed-4784639ac7fc\",\"HasChanged\":null}},\"Description\":{\"LocalizedLabels\":[],\"UserLocalizedLabel\":null}}]}},{\"@odata.type\":\"#Microsoft.Dynamics.CRM.PicklistAttributeMetadata\",\"MetadataId\":\"0b5be0d8-9ab4-ef11-a72f-6045bd0a486c\",\"LogicalName\":\"mserp_iswarehouselocationdimensionactive\",\"SchemaName\":\"mserp_iswarehouselocationdimensionactive\",\"DisplayName\":{\"LocalizedLabels\":[{\"Label\":\"Active\",\"LanguageCode\":1033,\"IsManaged\":true,\"MetadataId\":\"659b1fb5-2be8-41f6-b4d0-d7b1b2baee04\",\"HasChanged\":null}],\"UserLocalizedLabel\":{\"Label\":\"Active\",\"LanguageCode\":1033,\"IsManaged\":true,\"MetadataId\":\"659b1fb5-2be8-41f6-b4d0-d7b1b2baee04\",\"HasChanged\":null}},\"OptionSet\":{\"MetadataId\":\"d4e2dc39-7db4-ef11-a72f-6045bd0a486c\",\"HasChanged\":null,\"IsCustomOptionSet\":true,\"IsGlobal\":true,\"IsManaged\":true,\"Name\":\"mserp_noyes\",\"ExternalTypeName\":\"NoYes\",\"OptionSetType\":\"Picklist\",\"IntroducedVersion\":\"1.0.0.0\",\"ParentOptionSetName\":null,\"Description\":{\"LocalizedLabels\":[],\"UserLocalizedLabel\":null},\"DisplayName\":{\"LocalizedLabels\":[{\"Label\":\"NoYes (mserp)\",\"LanguageCode\":1033,\"IsManaged\":true,\"MetadataId\":\"d5e2dc39-7db4-ef11-a72f-6045bd0a486c\",\"HasChanged\":null}],\"UserLocalizedLabel\":{\"Label\":\"NoYes (mserp)\",\"LanguageCode\":1033,\"IsManaged\":true,\"MetadataId\":\"d5e2dc39-7db4-ef11-a72f-6045bd0a486c\",\"HasChanged\":null}},\"IsCustomizable\":{\"Value\":true,\"CanBeChanged\":false,\"ManagedPropertyLogicalName\":\"iscustomizable\"},\"Options\":[{\"Value\":200000000,\"Color\":null,\"IsManaged\":true,\"ExternalValue\":\"No\",\"ParentValues\":[],\"Tag\":null,\"IsHidden\":false,\"MetadataId\":null,\"HasChanged\":null,\"Label\":{\"LocalizedLabels\":[{\"Label\":\"No\",\"LanguageCode\":1033,\"IsManaged\":true,\"MetadataId\":\"4738e8e9-d095-4f43-a072-34abcb3039bc\",\"HasChanged\":null}],\"UserLocalizedLabel\":{\"Label\":\"No\",\"LanguageCode\":1033,\"IsManaged\":true,\"MetadataId\":\"4738e8e9-d095-4f43-a072-34abcb3039bc\",\"HasChanged\":null}},\"Description\":{\"LocalizedLabels\":[],\"UserLocalizedLabel\":null}},{\"Value\":200000001,\"Color\":null,\"IsManaged\":true,\"ExternalValue\":\"Yes\",\"ParentValues\":[],\"Tag\":null,\"IsHidden\":false,\"MetadataId\":null,\"HasChanged\":null,\"Label\":{\"LocalizedLabels\":[{\"Label\":\"Yes\",\"LanguageCode\":1033,\"IsManaged\":true,\"MetadataId\":\"032d13c5-c04d-41ef-b5ed-4784639ac7fc\",\"HasChanged\":null}],\"UserLocalizedLabel\":{\"Label\":\"Yes\",\"LanguageCode\":1033,\"IsManaged\":true,\"MetadataId\":\"032d13c5-c04d-41ef-b5ed-4784639ac7fc\",\"HasChanged\":null}},\"Description\":{\"LocalizedLabels\":[],\"UserLocalizedLabel\":null}}]}}]}",
    "StateOptionSetAttribute": "{\"@odata.context\":\"https://aurorabapenv7cf94.crm10.dynamics.com/api/data/v9.0/$metadata#EntityDefinitions('mserp_entassetreleasedproductstoragedimensiondefaultsentity')/Attributes/Microsoft.Dynamics.CRM.StateAttributeMetadata(MetadataId,LogicalName,SchemaName,DisplayName,OptionSet())\",\"value\":[]}",
    "StatusOptionSetAttribute": "{\"@odata.context\":\"https://aurorabapenv7cf94.crm10.dynamics.com/api/data/v9.0/$metadata#EntityDefinitions('mserp_entassetreleasedproductstoragedimensiondefaultsentity')/Attributes/Microsoft.Dynamics.CRM.StatusAttributeMetadata(MetadataId,LogicalName,SchemaName,DisplayName,OptionSet())\",\"value\":[]}",
    "TableName": "mserp_entassetreleasedproductstoragedimensiondefaultsentity",
    "Views": "{\"@odata.context\":\"https://aurorabapenv7cf94.crm10.dynamics.com/api/data/v9.0/$metadata#savedqueries(savedqueryid,name,querytype)\",\"value\":[{\"@odata.etag\":\"W/\\\"7401016\\\"\",\"savedqueryid\":\"65d365d1-aee0-cc5b-4002-4fa85c8aeadb\",\"name\":\"All Asset management released products storage dimension defaults (mserp)\",\"querytype\":0},{\"@odata.etag\":\"W/\\\"7400992\\\"\",\"savedqueryid\":\"ba4d5fa5-a633-dd7d-62f3-5672ebc675b3\",\"name\":\"Asset management released products storage dimension defaults (mserp) Advanced Find View\",\"querytype\":1},{\"@odata.etag\":\"W/\\\"7400968\\\"\",\"savedqueryid\":\"9f9854ca-d908-d710-7a04-6e938a63145d\",\"name\":\"Asset management released products storage dimension defaults (mserp) Associated View\",\"querytype\":2},{\"@odata.etag\":\"W/\\\"7400980\\\"\",\"savedqueryid\":\"f8d13024-8c4b-2a85-7adb-bef4c73e6ae2\",\"name\":\"Asset management released products storage dimension defaults (mserp) Lookup View\",\"querytype\":64}]}"
  },
  "UnusedDataSources": {},
  "webApiVersion": "v9.0"
}