{
  "components": [
    {
      "Capabilities": {
        "PCFExternalServiceUsageAllowed": false
      },
      "ComponentName": "CustomControl",
      "Identifier": "msdyn_MscrmControls.Common.A11yFocusTrap",
      "IdentifierType": 0
    },
    {
      "Capabilities": {
        "PCFExternalServiceUsageAllowed": false
      },
      "ComponentName": "CustomControl",
      "Identifier": "msdyn_MscrmControls.Common.A11yFocusTrap",
      "IdentifierType": 0
    },
    {
      "Capabilities": {
        "PCFExternalServiceUsageAllowed": false
      },
      "ComponentName": "CustomControl",
      "Identifier": "msdyn_MscrmControls.Common.A11yFocusTrap",
      "IdentifierType": 0
    },
    {
      "Capabilities": {
        "PCFExternalServiceUsageAllowed": false
      },
      "ComponentName": "CustomControl",
      "Identifier": "msdyn_MscrmControls.Common.A11yFocusTrap",
      "IdentifierType": 0
    }
  ],
  "DatasetName": "default.cds",
  "EntityName": "Asset management maintenance service levels V2 (mserp)",
  "InstanceUrl": "https://aurorabapenv7cf94.crm10.dynamics.com/",
  "LocalReferenceDSJson": {
    "entitySetName": "mserp_entassetmaintenanceassetservicelevelv2entities",
    "logicalName": "mserp_entassetmaintenanceassetservicelevelv2entity"
  },
  "state": "Configured",
  "TableDefinition": {
    "BooleanOptionSetAttribute": "{\"@odata.context\":\"https://aurorabapenv7cf94.crm10.dynamics.com/api/data/v9.0/$metadata#EntityDefinitions('mserp_entassetmaintenanceassetservicelevelv2entity')/Attributes/Microsoft.Dynamics.CRM.BooleanAttributeMetadata(MetadataId,LogicalName,SchemaName,DisplayName,OptionSet())\",\"value\":[]}",
    "DefaultPublicView": "{\"@odata.context\":\"https://aurorabapenv7cf94.crm10.dynamics.com/api/data/v9.0/$metadata#savedqueries(layoutxml)\",\"value\":[{\"@odata.etag\":\"W/\\\"6827540\\\"\",\"layoutxml\":\"<grid name=\\\"resultset\\\" object=\\\"11364\\\" jump=\\\"mserp_primaryfield\\\" select=\\\"1\\\" icon=\\\"1\\\" preview=\\\"1\\\"><row name=\\\"result\\\" id=\\\"mserp_entassetmaintenanceassetservicelevelv2entityid\\\"><cell name=\\\"mserp_primaryfield\\\" width=\\\"300\\\" /></row></grid>\",\"savedqueryid\":\"d5ef1b84-d0f0-b530-2d1a-e728010ab987\"}]}",
    "EntityMetadata": "{\"@odata.context\":\"https://aurorabapenv7cf94.crm10.dynamics.com/api/data/v9.0/$metadata#EntityDefinitions(MetadataId,LogicalName,DisplayCollectionName,EntitySetName,Description,HasNotes,IsActivity,IsIntersect,IsManaged,TableType,IsPrivate,IsLogicalEntity,PrimaryIdAttribute,PrimaryNameAttribute,ObjectTypeCode,OwnershipType,Privileges,IsAvailableOffline,IsOfflineInMobileClient,Attributes(),ManyToOneRelationships(),OneToManyRelationships(),ManyToManyRelationships())/$entity\",\"MetadataId\":\"47183353-98b4-ef11-a72f-6045bd0a486c\",\"IsActivity\":false,\"IsAvailableOffline\":false,\"IsIntersect\":false,\"IsManaged\":true,\"LogicalName\":\"mserp_entassetmaintenanceassetservicelevelv2entity\",\"ObjectTypeCode\":11364,\"OwnershipType\":\"OrganizationOwned\",\"PrimaryNameAttribute\":\"mserp_primaryfield\",\"PrimaryIdAttribute\":\"mserp_entassetmaintenanceassetservicelevelv2entityid\",\"EntitySetName\":\"mserp_entassetmaintenanceassetservicelevelv2entities\",\"IsPrivate\":false,\"IsLogicalEntity\":false,\"HasNotes\":false,\"TableType\":\"Virtual\",\"Description\":{\"LocalizedLabels\":[],\"UserLocalizedLabel\":null},\"DisplayCollectionName\":{\"LocalizedLabels\":[{\"Label\":\"Asset management maintenance service levels V2 (mserp)\",\"LanguageCode\":1033,\"IsManaged\":true,\"MetadataId\":\"536a8241-69dc-47e7-b78b-bae19948eeb7\",\"HasChanged\":null}],\"UserLocalizedLabel\":{\"Label\":\"Asset management maintenance service levels V2 (mserp)\",\"LanguageCode\":1033,\"IsManaged\":true,\"MetadataId\":\"536a8241-69dc-47e7-b78b-bae19948eeb7\",\"HasChanged\":null}},\"IsOfflineInMobileClient\":{\"Value\":false,\"CanBeChanged\":true,\"ManagedPropertyLogicalName\":\"canmodifymobileclientoffline\"},\"Privileges\":[{\"CanBeBasic\":false,\"CanBeDeep\":false,\"CanBeGlobal\":true,\"CanBeLocal\":false,\"CanBeEntityReference\":false,\"CanBeParentEntityReference\":false,\"CanBeRecordFilter\":false,\"Name\":\"prvCreatemserp_entassetmaintenanceassetservicelevelv2entity\",\"PrivilegeId\":\"5195eadd-28f0-4df2-931e-3acef25efa2e\",\"PrivilegeType\":\"Create\"},{\"CanBeBasic\":false,\"CanBeDeep\":false,\"CanBeGlobal\":true,\"CanBeLocal\":false,\"CanBeEntityReference\":false,\"CanBeParentEntityReference\":false,\"CanBeRecordFilter\":false,\"Name\":\"prvReadmserp_entassetmaintenanceassetservicelevelv2entity\",\"PrivilegeId\":\"9c1e9390-1206-4800-9374-c8239116544e\",\"PrivilegeType\":\"Read\"},{\"CanBeBasic\":false,\"CanBeDeep\":false,\"CanBeGlobal\":true,\"CanBeLocal\":false,\"CanBeEntityReference\":false,\"CanBeParentEntityReference\":false,\"CanBeRecordFilter\":false,\"Name\":\"prvWritemserp_entassetmaintenanceassetservicelevelv2entity\",\"PrivilegeId\":\"5b6559a8-572d-4c6c-9f30-bf98655dab18\",\"PrivilegeType\":\"Write\"},{\"CanBeBasic\":false,\"CanBeDeep\":false,\"CanBeGlobal\":true,\"CanBeLocal\":false,\"CanBeEntityReference\":false,\"CanBeParentEntityReference\":false,\"CanBeRecordFilter\":false,\"Name\":\"prvDeletemserp_entassetmaintenanceassetservicelevelv2entity\",\"PrivilegeId\":\"adcc58c6-054f-4959-85ea-2131ac121cef\",\"PrivilegeType\":\"Delete\"},{\"CanBeBasic\":false,\"CanBeDeep\":false,\"CanBeGlobal\":true,\"CanBeLocal\":false,\"CanBeEntityReference\":false,\"CanBeParentEntityReference\":false,\"CanBeRecordFilter\":false,\"Name\":\"prvAppendmserp_entassetmaintenanceassetservicelevelv2entity\",\"PrivilegeId\":\"b101afc1-bfc5-4722-8afc-4f0c7f968c36\",\"PrivilegeType\":\"Append\"},{\"CanBeBasic\":false,\"CanBeDeep\":false,\"CanBeGlobal\":true,\"CanBeLocal\":false,\"CanBeEntityReference\":false,\"CanBeParentEntityReference\":false,\"CanBeRecordFilter\":false,\"Name\":\"prvAppendTomserp_entassetmaintenanceassetservicelevelv2entity\",\"PrivilegeId\":\"1961c98e-888a-4d27-9782-84d4210d1528\",\"PrivilegeType\":\"AppendTo\"}],\"Attributes\":[{\"@odata.type\":\"#Microsoft.Dynamics.CRM.StringAttributeMetadata\",\"MetadataId\":\"c7183353-98b4-ef11-a72f-6045bd0a486c\",\"HasChanged\":null,\"AttributeOf\":null,\"AttributeType\":\"String\",\"ColumnNumber\":12,\"DeprecatedVersion\":null,\"IntroducedVersion\":\"1.0.0.0\",\"EntityLogicalName\":\"mserp_entassetmaintenanceassetservicelevelv2entity\",\"IsCustomAttribute\":true,\"IsPrimaryId\":false,\"IsValidODataAttribute\":true,\"IsPrimaryName\":false,\"IsValidForCreate\":true,\"IsValidForRead\":true,\"IsValidForUpdate\":true,\"CanBeSecuredForRead\":false,\"CanBeSecuredForCreate\":false,\"CanBeSecuredForUpdate\":false,\"IsSecured\":false,\"IsRetrievable\":false,\"IsFilterable\":false,\"IsSearchable\":false,\"IsManaged\":true,\"LinkedAttributeId\":null,\"LogicalName\":\"mserp_dataareaid\",\"IsValidForForm\":true,\"IsRequiredForForm\":false,\"IsValidForGrid\":true,\"SchemaName\":\"mserp_dataareaid\",\"ExternalName\":\"dataAreaId\",\"IsLogical\":false,\"IsDataSourceSecret\":false,\"InheritsFrom\":null,\"CreatedOn\":\"2024-12-07T12:39:49Z\",\"ModifiedOn\":\"2024-12-07T12:39:49Z\",\"SourceType\":0,\"AutoNumberFormat\":null,\"Format\":\"Text\",\"ImeMode\":\"Auto\",\"MaxLength\":4,\"YomiOf\":null,\"IsLocalizable\":false,\"DatabaseLength\":8,\"FormulaDefinition\":\"\",\"SourceTypeMask\":0,\"AttributeTypeName\":{\"Value\":\"StringType\"},\"Description\":{\"LocalizedLabels\":[],\"UserLocalizedLabel\":null},\"DisplayName\":{\"LocalizedLabels\":[{\"Label\":\"Company Code\",\"LanguageCode\":1033,\"IsManaged\":true,\"MetadataId\":\"bed719db-3223-47b1-ad80-cb02f3c53150\",\"HasChanged\":null}],\"UserLocalizedLabel\":{\"Label\":\"Company Code\",\"LanguageCode\":1033,\"IsManaged\":true,\"MetadataId\":\"bed719db-3223-47b1-ad80-cb02f3c53150\",\"HasChanged\":null}},\"IsAuditEnabled\":{\"Value\":true,\"CanBeChanged\":true,\"ManagedPropertyLogicalName\":\"canmodifyauditsettings\"},\"IsGlobalFilterEnabled\":{\"Value\":false,\"CanBeChanged\":true,\"ManagedPropertyLogicalName\":\"canmodifyglobalfiltersettings\"},\"IsSortableEnabled\":{\"Value\":false,\"CanBeChanged\":true,\"ManagedPropertyLogicalName\":\"canmodifyissortablesettings\"},\"IsCustomizable\":{\"Value\":false,\"CanBeChanged\":false,\"ManagedPropertyLogicalName\":\"iscustomizable\"},\"IsRenameable\":{\"Value\":true,\"CanBeChanged\":false,\"ManagedPropertyLogicalName\":\"isrenameable\"},\"IsValidForAdvancedFind\":{\"Value\":true,\"CanBeChanged\":true,\"ManagedPropertyLogicalName\":\"canmodifysearchsettings\"},\"RequiredLevel\":{\"Value\":\"Recommended\",\"CanBeChanged\":true,\"ManagedPropertyLogicalName\":\"canmodifyrequirementlevelsettings\"},\"CanModifyAdditionalSettings\":{\"Value\":true,\"CanBeChanged\":false,\"ManagedPropertyLogicalName\":\"canmodifyadditionalsettings\"},\"Settings\":[],\"FormatName\":{\"Value\":\"Text\"}},{\"@odata.type\":\"#Microsoft.Dynamics.CRM.LookupAttributeMetadata\",\"MetadataId\":\"3559c02d-458d-4b8a-b0f5-9780ed2280ff\",\"HasChanged\":null,\"AttributeOf\":null,\"AttributeType\":\"Lookup\",\"ColumnNumber\":13,\"DeprecatedVersion\":null,\"IntroducedVersion\":\"1.0.0.0\",\"EntityLogicalName\":\"mserp_entassetmaintenanceassetservicelevelv2entity\",\"IsCustomAttribute\":true,\"IsPrimaryId\":false,\"IsValidODataAttribute\":true,\"IsPrimaryName\":false,\"IsValidForCreate\":true,\"IsValidForRead\":true,\"IsValidForUpdate\":true,\"CanBeSecuredForRead\":true,\"CanBeSecuredForCreate\":true,\"CanBeSecuredForUpdate\":true,\"IsSecured\":false,\"IsRetrievable\":false,\"IsFilterable\":false,\"IsSearchable\":false,\"IsManaged\":true,\"LinkedAttributeId\":null,\"LogicalName\":\"mserp_dataareaid_id\",\"IsValidForForm\":true,\"IsRequiredForForm\":false,\"IsValidForGrid\":true,\"SchemaName\":\"mserp_dataAreaId_id\",\"ExternalName\":\"dataAreaId\",\"IsLogical\":false,\"IsDataSourceSecret\":false,\"InheritsFrom\":null,\"CreatedOn\":\"2024-12-07T12:39:49Z\",\"ModifiedOn\":\"2024-12-07T12:39:49Z\",\"SourceType\":null,\"AutoNumberFormat\":null,\"Targets\":[\"cdm_company\"],\"Format\":\"None\",\"AttributeTypeName\":{\"Value\":\"LookupType\"},\"Description\":{\"LocalizedLabels\":[],\"UserLocalizedLabel\":null},\"DisplayName\":{\"LocalizedLabels\":[{\"Label\":\"Company\",\"LanguageCode\":1033,\"IsManaged\":true,\"MetadataId\":\"e507519a-f1f9-4525-abf5-de6bb215e764\",\"HasChanged\":null}],\"UserLocalizedLabel\":{\"Label\":\"Company\",\"LanguageCode\":1033,\"IsManaged\":true,\"MetadataId\":\"e507519a-f1f9-4525-abf5-de6bb215e764\",\"HasChanged\":null}},\"IsAuditEnabled\":{\"Value\":false,\"CanBeChanged\":true,\"ManagedPropertyLogicalName\":\"canmodifyauditsettings\"},\"IsGlobalFilterEnabled\":{\"Value\":false,\"CanBeChanged\":true,\"ManagedPropertyLogicalName\":\"canmodifyglobalfiltersettings\"},\"IsSortableEnabled\":{\"Value\":false,\"CanBeChanged\":true,\"ManagedPropertyLogicalName\":\"canmodifyissortablesettings\"},\"IsCustomizable\":{\"Value\":true,\"CanBeChanged\":false,\"ManagedPropertyLogicalName\":\"iscustomizable\"},\"IsRenameable\":{\"Value\":true,\"CanBeChanged\":false,\"ManagedPropertyLogicalName\":\"isrenameable\"},\"IsValidForAdvancedFind\":{\"Value\":true,\"CanBeChanged\":true,\"ManagedPropertyLogicalName\":\"canmodifysearchsettings\"},\"RequiredLevel\":{\"Value\":\"Recommended\",\"CanBeChanged\":true,\"ManagedPropertyLogicalName\":\"canmodifyrequirementlevelsettings\"},\"CanModifyAdditionalSettings\":{\"Value\":true,\"CanBeChanged\":false,\"ManagedPropertyLogicalName\":\"canmodifyadditionalsettings\"},\"Settings\":[]},{\"@odata.type\":\"#Microsoft.Dynamics.CRM.StringAttributeMetadata\",\"MetadataId\":\"4332d351-e3f8-47a3-8f56-1c0f94df8d65\",\"HasChanged\":null,\"AttributeOf\":\"mserp_dataareaid_id\",\"AttributeType\":\"String\",\"ColumnNumber\":14,\"DeprecatedVersion\":null,\"IntroducedVersion\":\"1.0.0.0\",\"EntityLogicalName\":\"mserp_entassetmaintenanceassetservicelevelv2entity\",\"IsCustomAttribute\":true,\"IsPrimaryId\":false,\"IsValidODataAttribute\":false,\"IsPrimaryName\":false,\"IsValidForCreate\":false,\"IsValidForRead\":true,\"IsValidForUpdate\":false,\"CanBeSecuredForRead\":false,\"CanBeSecuredForCreate\":false,\"CanBeSecuredForUpdate\":false,\"IsSecured\":false,\"IsRetrievable\":false,\"IsFilterable\":false,\"IsSearchable\":false,\"IsManaged\":false,\"LinkedAttributeId\":null,\"LogicalName\":\"mserp_dataareaid_idname\",\"IsValidForForm\":false,\"IsRequiredForForm\":false,\"IsValidForGrid\":false,\"SchemaName\":\"mserp_dataAreaId_idName\",\"ExternalName\":null,\"IsLogical\":true,\"IsDataSourceSecret\":false,\"InheritsFrom\":null,\"CreatedOn\":\"2024-12-07T12:39:49Z\",\"ModifiedOn\":\"2024-12-07T12:39:49Z\",\"SourceType\":0,\"AutoNumberFormat\":null,\"Format\":\"Text\",\"ImeMode\":\"Auto\",\"MaxLength\":20,\"YomiOf\":null,\"IsLocalizable\":false,\"DatabaseLength\":40,\"FormulaDefinition\":\"\",\"SourceTypeMask\":0,\"AttributeTypeName\":{\"Value\":\"StringType\"},\"Description\":{\"LocalizedLabels\":[],\"UserLocalizedLabel\":null},\"DisplayName\":{\"LocalizedLabels\":[],\"UserLocalizedLabel\":null},\"IsAuditEnabled\":{\"Value\":true,\"CanBeChanged\":true,\"ManagedPropertyLogicalName\":\"canmodifyauditsettings\"},\"IsGlobalFilterEnabled\":{\"Value\":false,\"CanBeChanged\":true,\"ManagedPropertyLogicalName\":\"canmodifyglobalfiltersettings\"},\"IsSortableEnabled\":{\"Value\":false,\"CanBeChanged\":true,\"ManagedPropertyLogicalName\":\"canmodifyissortablesettings\"},\"IsCustomizable\":{\"Value\":true,\"CanBeChanged\":true,\"ManagedPropertyLogicalName\":\"iscustomizable\"},\"IsRenameable\":{\"Value\":true,\"CanBeChanged\":true,\"ManagedPropertyLogicalName\":\"isrenameable\"},\"IsValidForAdvancedFind\":{\"Value\":false,\"CanBeChanged\":true,\"ManagedPropertyLogicalName\":\"canmodifysearchsettings\"},\"RequiredLevel\":{\"Value\":\"None\",\"CanBeChanged\":true,\"ManagedPropertyLogicalName\":\"canmodifyrequirementlevelsettings\"},\"CanModifyAdditionalSettings\":{\"Value\":true,\"CanBeChanged\":true,\"ManagedPropertyLogicalName\":\"canmodifyadditionalsettings\"},\"Settings\":[],\"FormatName\":{\"Value\":\"Text\"}},{\"MetadataId\":\"a95d5446-4279-44e5-90d1-3468edb3e5b2\",\"HasChanged\":null,\"AttributeOf\":null,\"AttributeType\":\"Uniqueidentifier\",\"ColumnNumber\":1,\"DeprecatedVersion\":null,\"IntroducedVersion\":\"1.0.0.0\",\"EntityLogicalName\":\"mserp_entassetmaintenanceassetservicelevelv2entity\",\"IsCustomAttribute\":false,\"IsPrimaryId\":true,\"IsValidODataAttribute\":true,\"IsPrimaryName\":false,\"IsValidForCreate\":true,\"IsValidForRead\":true,\"IsValidForUpdate\":false,\"CanBeSecuredForRead\":false,\"CanBeSecuredForCreate\":false,\"CanBeSecuredForUpdate\":false,\"IsSecured\":false,\"IsRetrievable\":true,\"IsFilterable\":true,\"IsSearchable\":false,\"IsManaged\":true,\"LinkedAttributeId\":null,\"LogicalName\":\"mserp_entassetmaintenanceassetservicelevelv2entityid\",\"IsValidForForm\":false,\"IsRequiredForForm\":false,\"IsValidForGrid\":false,\"SchemaName\":\"mserp_entassetmaintenanceassetservicelevelv2entityId\",\"ExternalName\":null,\"IsLogical\":false,\"IsDataSourceSecret\":false,\"InheritsFrom\":null,\"CreatedOn\":\"2024-12-07T12:39:47Z\",\"ModifiedOn\":\"2024-12-07T12:39:47Z\",\"SourceType\":null,\"AutoNumberFormat\":null,\"AttributeTypeName\":{\"Value\":\"UniqueidentifierType\"},\"Description\":{\"LocalizedLabels\":[{\"Label\":\"Unique identifier for entity instances\",\"LanguageCode\":1033,\"IsManaged\":true,\"MetadataId\":\"5e183353-98b4-ef11-a72f-6045bd0a486c\",\"HasChanged\":null}],\"UserLocalizedLabel\":{\"Label\":\"Unique identifier for entity instances\",\"LanguageCode\":1033,\"IsManaged\":true,\"MetadataId\":\"5e183353-98b4-ef11-a72f-6045bd0a486c\",\"HasChanged\":null}},\"DisplayName\":{\"LocalizedLabels\":[{\"Label\":\"Asset management maintenance service levels V2 (mserp)\",\"LanguageCode\":1033,\"IsManaged\":true,\"MetadataId\":\"5f183353-98b4-ef11-a72f-6045bd0a486c\",\"HasChanged\":null}],\"UserLocalizedLabel\":{\"Label\":\"Asset management maintenance service levels V2 (mserp)\",\"LanguageCode\":1033,\"IsManaged\":true,\"MetadataId\":\"5f183353-98b4-ef11-a72f-6045bd0a486c\",\"HasChanged\":null}},\"IsAuditEnabled\":{\"Value\":false,\"CanBeChanged\":false,\"ManagedPropertyLogicalName\":\"canmodifyauditsettings\"},\"IsGlobalFilterEnabled\":{\"Value\":false,\"CanBeChanged\":true,\"ManagedPropertyLogicalName\":\"canmodifyglobalfiltersettings\"},\"IsSortableEnabled\":{\"Value\":false,\"CanBeChanged\":true,\"ManagedPropertyLogicalName\":\"canmodifyissortablesettings\"},\"IsCustomizable\":{\"Value\":true,\"CanBeChanged\":false,\"ManagedPropertyLogicalName\":\"iscustomizable\"},\"IsRenameable\":{\"Value\":true,\"CanBeChanged\":false,\"ManagedPropertyLogicalName\":\"isrenameable\"},\"IsValidForAdvancedFind\":{\"Value\":true,\"CanBeChanged\":true,\"ManagedPropertyLogicalName\":\"canmodifysearchsettings\"},\"RequiredLevel\":{\"Value\":\"SystemRequired\",\"CanBeChanged\":false,\"ManagedPropertyLogicalName\":\"canmodifyrequirementlevelsettings\"},\"CanModifyAdditionalSettings\":{\"Value\":true,\"CanBeChanged\":false,\"ManagedPropertyLogicalName\":\"canmodifyadditionalsettings\"},\"Settings\":[]},{\"@odata.type\":\"#Microsoft.Dynamics.CRM.LookupAttributeMetadata\",\"MetadataId\":\"d664bee8-bcb2-4984-9e9d-ffecc4d84d01\",\"HasChanged\":null,\"AttributeOf\":null,\"AttributeType\":\"Lookup\",\"ColumnNumber\":19,\"DeprecatedVersion\":null,\"IntroducedVersion\":\"1.0.0.0\",\"EntityLogicalName\":\"mserp_entassetmaintenanceassetservicelevelv2entity\",\"IsCustomAttribute\":true,\"IsPrimaryId\":false,\"IsValidODataAttribute\":true,\"IsPrimaryName\":false,\"IsValidForCreate\":true,\"IsValidForRead\":true,\"IsValidForUpdate\":true,\"CanBeSecuredForRead\":true,\"CanBeSecuredForCreate\":true,\"CanBeSecuredForUpdate\":true,\"IsSecured\":false,\"IsRetrievable\":false,\"IsFilterable\":false,\"IsSearchable\":false,\"IsManaged\":true,\"LinkedAttributeId\":null,\"LogicalName\":\"mserp_fk_functionallocation_id\",\"IsValidForForm\":true,\"IsRequiredForForm\":false,\"IsValidForGrid\":true,\"SchemaName\":\"mserp_FK_FunctionalLocation_id\",\"ExternalName\":\"FK_FunctionalLocation\",\"IsLogical\":false,\"IsDataSourceSecret\":false,\"InheritsFrom\":null,\"CreatedOn\":\"2024-12-07T12:40:41Z\",\"ModifiedOn\":\"2024-12-07T12:40:41Z\",\"SourceType\":null,\"AutoNumberFormat\":null,\"Targets\":[\"mserp_entassetmaintenancefunctionallocationentity\"],\"Format\":\"None\",\"AttributeTypeName\":{\"Value\":\"LookupType\"},\"Description\":{\"LocalizedLabels\":[],\"UserLocalizedLabel\":null},\"DisplayName\":{\"LocalizedLabels\":[{\"Label\":\"Asset management functional locations\",\"LanguageCode\":1033,\"IsManaged\":true,\"MetadataId\":\"09cd36d7-44cf-49fd-a63b-c7641b6f9d2d\",\"HasChanged\":null}],\"UserLocalizedLabel\":{\"Label\":\"Asset management functional locations\",\"LanguageCode\":1033,\"IsManaged\":true,\"MetadataId\":\"09cd36d7-44cf-49fd-a63b-c7641b6f9d2d\",\"HasChanged\":null}},\"IsAuditEnabled\":{\"Value\":false,\"CanBeChanged\":true,\"ManagedPropertyLogicalName\":\"canmodifyauditsettings\"},\"IsGlobalFilterEnabled\":{\"Value\":false,\"CanBeChanged\":true,\"ManagedPropertyLogicalName\":\"canmodifyglobalfiltersettings\"},\"IsSortableEnabled\":{\"Value\":false,\"CanBeChanged\":true,\"ManagedPropertyLogicalName\":\"canmodifyissortablesettings\"},\"IsCustomizable\":{\"Value\":true,\"CanBeChanged\":false,\"ManagedPropertyLogicalName\":\"iscustomizable\"},\"IsRenameable\":{\"Value\":true,\"CanBeChanged\":false,\"ManagedPropertyLogicalName\":\"isrenameable\"},\"IsValidForAdvancedFind\":{\"Value\":true,\"CanBeChanged\":true,\"ManagedPropertyLogicalName\":\"canmodifysearchsettings\"},\"RequiredLevel\":{\"Value\":\"None\",\"CanBeChanged\":true,\"ManagedPropertyLogicalName\":\"canmodifyrequirementlevelsettings\"},\"CanModifyAdditionalSettings\":{\"Value\":true,\"CanBeChanged\":false,\"ManagedPropertyLogicalName\":\"canmodifyadditionalsettings\"},\"Settings\":[]},{\"@odata.type\":\"#Microsoft.Dynamics.CRM.StringAttributeMetadata\",\"MetadataId\":\"1e2b3938-7343-4ae4-bed0-76b71fb915b2\",\"HasChanged\":null,\"AttributeOf\":\"mserp_fk_functionallocation_id\",\"AttributeType\":\"String\",\"ColumnNumber\":20,\"DeprecatedVersion\":null,\"IntroducedVersion\":\"1.0.0.0\",\"EntityLogicalName\":\"mserp_entassetmaintenanceassetservicelevelv2entity\",\"IsCustomAttribute\":true,\"IsPrimaryId\":false,\"IsValidODataAttribute\":false,\"IsPrimaryName\":false,\"IsValidForCreate\":false,\"IsValidForRead\":true,\"IsValidForUpdate\":false,\"CanBeSecuredForRead\":false,\"CanBeSecuredForCreate\":false,\"CanBeSecuredForUpdate\":false,\"IsSecured\":false,\"IsRetrievable\":false,\"IsFilterable\":false,\"IsSearchable\":false,\"IsManaged\":false,\"LinkedAttributeId\":null,\"LogicalName\":\"mserp_fk_functionallocation_idname\",\"IsValidForForm\":false,\"IsRequiredForForm\":false,\"IsValidForGrid\":false,\"SchemaName\":\"mserp_FK_FunctionalLocation_idName\",\"ExternalName\":null,\"IsLogical\":true,\"IsDataSourceSecret\":false,\"InheritsFrom\":null,\"CreatedOn\":\"2024-12-07T12:40:41Z\",\"ModifiedOn\":\"2024-12-07T12:40:41Z\",\"SourceType\":0,\"AutoNumberFormat\":null,\"Format\":\"Text\",\"ImeMode\":\"Auto\",\"MaxLength\":50,\"YomiOf\":null,\"IsLocalizable\":false,\"DatabaseLength\":100,\"FormulaDefinition\":\"\",\"SourceTypeMask\":0,\"AttributeTypeName\":{\"Value\":\"StringType\"},\"Description\":{\"LocalizedLabels\":[],\"UserLocalizedLabel\":null},\"DisplayName\":{\"LocalizedLabels\":[],\"UserLocalizedLabel\":null},\"IsAuditEnabled\":{\"Value\":true,\"CanBeChanged\":true,\"ManagedPropertyLogicalName\":\"canmodifyauditsettings\"},\"IsGlobalFilterEnabled\":{\"Value\":false,\"CanBeChanged\":true,\"ManagedPropertyLogicalName\":\"canmodifyglobalfiltersettings\"},\"IsSortableEnabled\":{\"Value\":false,\"CanBeChanged\":true,\"ManagedPropertyLogicalName\":\"canmodifyissortablesettings\"},\"IsCustomizable\":{\"Value\":true,\"CanBeChanged\":true,\"ManagedPropertyLogicalName\":\"iscustomizable\"},\"IsRenameable\":{\"Value\":true,\"CanBeChanged\":true,\"ManagedPropertyLogicalName\":\"isrenameable\"},\"IsValidForAdvancedFind\":{\"Value\":false,\"CanBeChanged\":true,\"ManagedPropertyLogicalName\":\"canmodifysearchsettings\"},\"RequiredLevel\":{\"Value\":\"None\",\"CanBeChanged\":true,\"ManagedPropertyLogicalName\":\"canmodifyrequirementlevelsettings\"},\"CanModifyAdditionalSettings\":{\"Value\":true,\"CanBeChanged\":true,\"ManagedPropertyLogicalName\":\"canmodifyadditionalsettings\"},\"Settings\":[],\"FormatName\":{\"Value\":\"Text\"}},{\"@odata.type\":\"#Microsoft.Dynamics.CRM.LookupAttributeMetadata\",\"MetadataId\":\"2342aa0c-c8b9-49ca-ba60-c16b7580b2d1\",\"HasChanged\":null,\"AttributeOf\":null,\"AttributeType\":\"Lookup\",\"ColumnNumber\":15,\"DeprecatedVersion\":null,\"IntroducedVersion\":\"1.0.0.0\",\"EntityLogicalName\":\"mserp_entassetmaintenanceassetservicelevelv2entity\",\"IsCustomAttribute\":true,\"IsPrimaryId\":false,\"IsValidODataAttribute\":true,\"IsPrimaryName\":false,\"IsValidForCreate\":true,\"IsValidForRead\":true,\"IsValidForUpdate\":true,\"CanBeSecuredForRead\":true,\"CanBeSecuredForCreate\":true,\"CanBeSecuredForUpdate\":true,\"IsSecured\":false,\"IsRetrievable\":false,\"IsFilterable\":false,\"IsSearchable\":false,\"IsManaged\":true,\"LinkedAttributeId\":null,\"LogicalName\":\"mserp_fk_maintenanceasset_id\",\"IsValidForForm\":true,\"IsRequiredForForm\":false,\"IsValidForGrid\":true,\"SchemaName\":\"mserp_FK_MaintenanceAsset_id\",\"ExternalName\":\"FK_MaintenanceAsset\",\"IsLogical\":false,\"IsDataSourceSecret\":false,\"InheritsFrom\":null,\"CreatedOn\":\"2024-12-07T12:40:07Z\",\"ModifiedOn\":\"2024-12-07T12:40:07Z\",\"SourceType\":null,\"AutoNumberFormat\":null,\"Targets\":[\"mserp_entassetmaintenanceassetv3entity\"],\"Format\":\"None\",\"AttributeTypeName\":{\"Value\":\"LookupType\"},\"Description\":{\"LocalizedLabels\":[],\"UserLocalizedLabel\":null},\"DisplayName\":{\"LocalizedLabels\":[{\"Label\":\"Assets entity view V3\",\"LanguageCode\":1033,\"IsManaged\":true,\"MetadataId\":\"2342392a-378e-4d2c-bb77-289f5bff8642\",\"HasChanged\":null}],\"UserLocalizedLabel\":{\"Label\":\"Assets entity view V3\",\"LanguageCode\":1033,\"IsManaged\":true,\"MetadataId\":\"2342392a-378e-4d2c-bb77-289f5bff8642\",\"HasChanged\":null}},\"IsAuditEnabled\":{\"Value\":false,\"CanBeChanged\":true,\"ManagedPropertyLogicalName\":\"canmodifyauditsettings\"},\"IsGlobalFilterEnabled\":{\"Value\":false,\"CanBeChanged\":true,\"ManagedPropertyLogicalName\":\"canmodifyglobalfiltersettings\"},\"IsSortableEnabled\":{\"Value\":false,\"CanBeChanged\":true,\"ManagedPropertyLogicalName\":\"canmodifyissortablesettings\"},\"IsCustomizable\":{\"Value\":true,\"CanBeChanged\":false,\"ManagedPropertyLogicalName\":\"iscustomizable\"},\"IsRenameable\":{\"Value\":true,\"CanBeChanged\":false,\"ManagedPropertyLogicalName\":\"isrenameable\"},\"IsValidForAdvancedFind\":{\"Value\":true,\"CanBeChanged\":true,\"ManagedPropertyLogicalName\":\"canmodifysearchsettings\"},\"RequiredLevel\":{\"Value\":\"None\",\"CanBeChanged\":true,\"ManagedPropertyLogicalName\":\"canmodifyrequirementlevelsettings\"},\"CanModifyAdditionalSettings\":{\"Value\":true,\"CanBeChanged\":false,\"ManagedPropertyLogicalName\":\"canmodifyadditionalsettings\"},\"Settings\":[]},{\"@odata.type\":\"#Microsoft.Dynamics.CRM.StringAttributeMetadata\",\"MetadataId\":\"02b03af7-01a3-4ba0-8715-94ddc53155a7\",\"HasChanged\":null,\"AttributeOf\":\"mserp_fk_maintenanceasset_id\",\"AttributeType\":\"String\",\"ColumnNumber\":16,\"DeprecatedVersion\":null,\"IntroducedVersion\":\"1.0.0.0\",\"EntityLogicalName\":\"mserp_entassetmaintenanceassetservicelevelv2entity\",\"IsCustomAttribute\":true,\"IsPrimaryId\":false,\"IsValidODataAttribute\":false,\"IsPrimaryName\":false,\"IsValidForCreate\":false,\"IsValidForRead\":true,\"IsValidForUpdate\":false,\"CanBeSecuredForRead\":false,\"CanBeSecuredForCreate\":false,\"CanBeSecuredForUpdate\":false,\"IsSecured\":false,\"IsRetrievable\":false,\"IsFilterable\":false,\"IsSearchable\":false,\"IsManaged\":false,\"LinkedAttributeId\":null,\"LogicalName\":\"mserp_fk_maintenanceasset_idname\",\"IsValidForForm\":false,\"IsRequiredForForm\":false,\"IsValidForGrid\":false,\"SchemaName\":\"mserp_FK_MaintenanceAsset_idName\",\"ExternalName\":null,\"IsLogical\":true,\"IsDataSourceSecret\":false,\"InheritsFrom\":null,\"CreatedOn\":\"2024-12-07T12:40:07Z\",\"ModifiedOn\":\"2024-12-07T12:40:07Z\",\"SourceType\":0,\"AutoNumberFormat\":null,\"Format\":\"Text\",\"ImeMode\":\"Auto\",\"MaxLength\":50,\"YomiOf\":null,\"IsLocalizable\":false,\"DatabaseLength\":100,\"FormulaDefinition\":\"\",\"SourceTypeMask\":0,\"AttributeTypeName\":{\"Value\":\"StringType\"},\"Description\":{\"LocalizedLabels\":[],\"UserLocalizedLabel\":null},\"DisplayName\":{\"LocalizedLabels\":[],\"UserLocalizedLabel\":null},\"IsAuditEnabled\":{\"Value\":true,\"CanBeChanged\":true,\"ManagedPropertyLogicalName\":\"canmodifyauditsettings\"},\"IsGlobalFilterEnabled\":{\"Value\":false,\"CanBeChanged\":true,\"ManagedPropertyLogicalName\":\"canmodifyglobalfiltersettings\"},\"IsSortableEnabled\":{\"Value\":false,\"CanBeChanged\":true,\"ManagedPropertyLogicalName\":\"canmodifyissortablesettings\"},\"IsCustomizable\":{\"Value\":true,\"CanBeChanged\":true,\"ManagedPropertyLogicalName\":\"iscustomizable\"},\"IsRenameable\":{\"Value\":true,\"CanBeChanged\":true,\"ManagedPropertyLogicalName\":\"isrenameable\"},\"IsValidForAdvancedFind\":{\"Value\":false,\"CanBeChanged\":true,\"ManagedPropertyLogicalName\":\"canmodifysearchsettings\"},\"RequiredLevel\":{\"Value\":\"None\",\"CanBeChanged\":true,\"ManagedPropertyLogicalName\":\"canmodifyrequirementlevelsettings\"},\"CanModifyAdditionalSettings\":{\"Value\":true,\"CanBeChanged\":true,\"ManagedPropertyLogicalName\":\"canmodifyadditionalsettings\"},\"Settings\":[],\"FormatName\":{\"Value\":\"Text\"}},{\"@odata.type\":\"#Microsoft.Dynamics.CRM.LookupAttributeMetadata\",\"MetadataId\":\"29dcc02a-fccc-4fbe-a106-29be58815b72\",\"HasChanged\":null,\"AttributeOf\":null,\"AttributeType\":\"Lookup\",\"ColumnNumber\":17,\"DeprecatedVersion\":null,\"IntroducedVersion\":\"1.0.0.0\",\"EntityLogicalName\":\"mserp_entassetmaintenanceassetservicelevelv2entity\",\"IsCustomAttribute\":true,\"IsPrimaryId\":false,\"IsValidODataAttribute\":true,\"IsPrimaryName\":false,\"IsValidForCreate\":true,\"IsValidForRead\":true,\"IsValidForUpdate\":true,\"CanBeSecuredForRead\":true,\"CanBeSecuredForCreate\":true,\"CanBeSecuredForUpdate\":true,\"IsSecured\":false,\"IsRetrievable\":false,\"IsFilterable\":false,\"IsSearchable\":false,\"IsManaged\":true,\"LinkedAttributeId\":null,\"LogicalName\":\"mserp_fk_model_id\",\"IsValidForForm\":true,\"IsRequiredForForm\":false,\"IsValidForGrid\":true,\"SchemaName\":\"mserp_FK_Model_id\",\"ExternalName\":\"FK_Model\",\"IsLogical\":false,\"IsDataSourceSecret\":false,\"InheritsFrom\":null,\"CreatedOn\":\"2024-12-07T12:40:24Z\",\"ModifiedOn\":\"2024-12-07T12:40:24Z\",\"SourceType\":null,\"AutoNumberFormat\":null,\"Targets\":[\"mserp_entassetmaintenancemodelentity\"],\"Format\":\"None\",\"AttributeTypeName\":{\"Value\":\"LookupType\"},\"Description\":{\"LocalizedLabels\":[],\"UserLocalizedLabel\":null},\"DisplayName\":{\"LocalizedLabels\":[{\"Label\":\"Asset management models\",\"LanguageCode\":1033,\"IsManaged\":true,\"MetadataId\":\"18d4d160-12f0-4719-adfd-a5dc447692a7\",\"HasChanged\":null}],\"UserLocalizedLabel\":{\"Label\":\"Asset management models\",\"LanguageCode\":1033,\"IsManaged\":true,\"MetadataId\":\"18d4d160-12f0-4719-adfd-a5dc447692a7\",\"HasChanged\":null}},\"IsAuditEnabled\":{\"Value\":false,\"CanBeChanged\":true,\"ManagedPropertyLogicalName\":\"canmodifyauditsettings\"},\"IsGlobalFilterEnabled\":{\"Value\":false,\"CanBeChanged\":true,\"ManagedPropertyLogicalName\":\"canmodifyglobalfiltersettings\"},\"IsSortableEnabled\":{\"Value\":false,\"CanBeChanged\":true,\"ManagedPropertyLogicalName\":\"canmodifyissortablesettings\"},\"IsCustomizable\":{\"Value\":true,\"CanBeChanged\":false,\"ManagedPropertyLogicalName\":\"iscustomizable\"},\"IsRenameable\":{\"Value\":true,\"CanBeChanged\":false,\"ManagedPropertyLogicalName\":\"isrenameable\"},\"IsValidForAdvancedFind\":{\"Value\":true,\"CanBeChanged\":true,\"ManagedPropertyLogicalName\":\"canmodifysearchsettings\"},\"RequiredLevel\":{\"Value\":\"None\",\"CanBeChanged\":true,\"ManagedPropertyLogicalName\":\"canmodifyrequirementlevelsettings\"},\"CanModifyAdditionalSettings\":{\"Value\":true,\"CanBeChanged\":false,\"ManagedPropertyLogicalName\":\"canmodifyadditionalsettings\"},\"Settings\":[]},{\"@odata.type\":\"#Microsoft.Dynamics.CRM.StringAttributeMetadata\",\"MetadataId\":\"30e2da0c-559a-4fcc-add1-8adbe01002ce\",\"HasChanged\":null,\"AttributeOf\":\"mserp_fk_model_id\",\"AttributeType\":\"String\",\"ColumnNumber\":18,\"DeprecatedVersion\":null,\"IntroducedVersion\":\"1.0.0.0\",\"EntityLogicalName\":\"mserp_entassetmaintenanceassetservicelevelv2entity\",\"IsCustomAttribute\":true,\"IsPrimaryId\":false,\"IsValidODataAttribute\":false,\"IsPrimaryName\":false,\"IsValidForCreate\":false,\"IsValidForRead\":true,\"IsValidForUpdate\":false,\"CanBeSecuredForRead\":false,\"CanBeSecuredForCreate\":false,\"CanBeSecuredForUpdate\":false,\"IsSecured\":false,\"IsRetrievable\":false,\"IsFilterable\":false,\"IsSearchable\":false,\"IsManaged\":false,\"LinkedAttributeId\":null,\"LogicalName\":\"mserp_fk_model_idname\",\"IsValidForForm\":false,\"IsRequiredForForm\":false,\"IsValidForGrid\":false,\"SchemaName\":\"mserp_FK_Model_idName\",\"ExternalName\":null,\"IsLogical\":true,\"IsDataSourceSecret\":false,\"InheritsFrom\":null,\"CreatedOn\":\"2024-12-07T12:40:24Z\",\"ModifiedOn\":\"2024-12-07T12:40:24Z\",\"SourceType\":0,\"AutoNumberFormat\":null,\"Format\":\"Text\",\"ImeMode\":\"Auto\",\"MaxLength\":256,\"YomiOf\":null,\"IsLocalizable\":false,\"DatabaseLength\":512,\"FormulaDefinition\":\"\",\"SourceTypeMask\":0,\"AttributeTypeName\":{\"Value\":\"StringType\"},\"Description\":{\"LocalizedLabels\":[],\"UserLocalizedLabel\":null},\"DisplayName\":{\"LocalizedLabels\":[],\"UserLocalizedLabel\":null},\"IsAuditEnabled\":{\"Value\":true,\"CanBeChanged\":true,\"ManagedPropertyLogicalName\":\"canmodifyauditsettings\"},\"IsGlobalFilterEnabled\":{\"Value\":false,\"CanBeChanged\":true,\"ManagedPropertyLogicalName\":\"canmodifyglobalfiltersettings\"},\"IsSortableEnabled\":{\"Value\":false,\"CanBeChanged\":true,\"ManagedPropertyLogicalName\":\"canmodifyissortablesettings\"},\"IsCustomizable\":{\"Value\":true,\"CanBeChanged\":true,\"ManagedPropertyLogicalName\":\"iscustomizable\"},\"IsRenameable\":{\"Value\":true,\"CanBeChanged\":true,\"ManagedPropertyLogicalName\":\"isrenameable\"},\"IsValidForAdvancedFind\":{\"Value\":false,\"CanBeChanged\":true,\"ManagedPropertyLogicalName\":\"canmodifysearchsettings\"},\"RequiredLevel\":{\"Value\":\"None\",\"CanBeChanged\":true,\"ManagedPropertyLogicalName\":\"canmodifyrequirementlevelsettings\"},\"CanModifyAdditionalSettings\":{\"Value\":true,\"CanBeChanged\":true,\"ManagedPropertyLogicalName\":\"canmodifyadditionalsettings\"},\"Settings\":[],\"FormatName\":{\"Value\":\"Text\"}},{\"@odata.type\":\"#Microsoft.Dynamics.CRM.LookupAttributeMetadata\",\"MetadataId\":\"a21e2661-9d83-4ab9-b777-342098ba4c12\",\"HasChanged\":null,\"AttributeOf\":null,\"AttributeType\":\"Lookup\",\"ColumnNumber\":21,\"DeprecatedVersion\":null,\"IntroducedVersion\":\"1.0.0.0\",\"EntityLogicalName\":\"mserp_entassetmaintenanceassetservicelevelv2entity\",\"IsCustomAttribute\":true,\"IsPrimaryId\":false,\"IsValidODataAttribute\":true,\"IsPrimaryName\":false,\"IsValidForCreate\":true,\"IsValidForRead\":true,\"IsValidForUpdate\":true,\"CanBeSecuredForRead\":true,\"CanBeSecuredForCreate\":true,\"CanBeSecuredForUpdate\":true,\"IsSecured\":false,\"IsRetrievable\":false,\"IsFilterable\":false,\"IsSearchable\":false,\"IsManaged\":true,\"LinkedAttributeId\":null,\"LogicalName\":\"mserp_fk_workordertype_id\",\"IsValidForForm\":true,\"IsRequiredForForm\":false,\"IsValidForGrid\":true,\"SchemaName\":\"mserp_FK_WorkOrderType_id\",\"ExternalName\":\"FK_WorkOrderType\",\"IsLogical\":false,\"IsDataSourceSecret\":false,\"InheritsFrom\":null,\"CreatedOn\":\"2024-12-07T12:55:29Z\",\"ModifiedOn\":\"2024-12-07T12:55:29Z\",\"SourceType\":null,\"AutoNumberFormat\":null,\"Targets\":[\"mserp_entassetmaintenanceworkordertypeentity\"],\"Format\":\"None\",\"AttributeTypeName\":{\"Value\":\"LookupType\"},\"Description\":{\"LocalizedLabels\":[],\"UserLocalizedLabel\":null},\"DisplayName\":{\"LocalizedLabels\":[{\"Label\":\"Asset management work order types\",\"LanguageCode\":1033,\"IsManaged\":true,\"MetadataId\":\"b9a1fe88-7e98-4b72-bb86-939e1b82782b\",\"HasChanged\":null}],\"UserLocalizedLabel\":{\"Label\":\"Asset management work order types\",\"LanguageCode\":1033,\"IsManaged\":true,\"MetadataId\":\"b9a1fe88-7e98-4b72-bb86-939e1b82782b\",\"HasChanged\":null}},\"IsAuditEnabled\":{\"Value\":false,\"CanBeChanged\":true,\"ManagedPropertyLogicalName\":\"canmodifyauditsettings\"},\"IsGlobalFilterEnabled\":{\"Value\":false,\"CanBeChanged\":true,\"ManagedPropertyLogicalName\":\"canmodifyglobalfiltersettings\"},\"IsSortableEnabled\":{\"Value\":false,\"CanBeChanged\":true,\"ManagedPropertyLogicalName\":\"canmodifyissortablesettings\"},\"IsCustomizable\":{\"Value\":true,\"CanBeChanged\":false,\"ManagedPropertyLogicalName\":\"iscustomizable\"},\"IsRenameable\":{\"Value\":true,\"CanBeChanged\":false,\"ManagedPropertyLogicalName\":\"isrenameable\"},\"IsValidForAdvancedFind\":{\"Value\":true,\"CanBeChanged\":true,\"ManagedPropertyLogicalName\":\"canmodifysearchsettings\"},\"RequiredLevel\":{\"Value\":\"None\",\"CanBeChanged\":true,\"ManagedPropertyLogicalName\":\"canmodifyrequirementlevelsettings\"},\"CanModifyAdditionalSettings\":{\"Value\":true,\"CanBeChanged\":false,\"ManagedPropertyLogicalName\":\"canmodifyadditionalsettings\"},\"Settings\":[]},{\"@odata.type\":\"#Microsoft.Dynamics.CRM.StringAttributeMetadata\",\"MetadataId\":\"cda56364-c41e-4b2c-9c4d-59a306b832d0\",\"HasChanged\":null,\"AttributeOf\":\"mserp_fk_workordertype_id\",\"AttributeType\":\"String\",\"ColumnNumber\":22,\"DeprecatedVersion\":null,\"IntroducedVersion\":\"1.0.0.0\",\"EntityLogicalName\":\"mserp_entassetmaintenanceassetservicelevelv2entity\",\"IsCustomAttribute\":true,\"IsPrimaryId\":false,\"IsValidODataAttribute\":false,\"IsPrimaryName\":false,\"IsValidForCreate\":false,\"IsValidForRead\":true,\"IsValidForUpdate\":false,\"CanBeSecuredForRead\":false,\"CanBeSecuredForCreate\":false,\"CanBeSecuredForUpdate\":false,\"IsSecured\":false,\"IsRetrievable\":false,\"IsFilterable\":false,\"IsSearchable\":false,\"IsManaged\":false,\"LinkedAttributeId\":null,\"LogicalName\":\"mserp_fk_workordertype_idname\",\"IsValidForForm\":false,\"IsRequiredForForm\":false,\"IsValidForGrid\":false,\"SchemaName\":\"mserp_FK_WorkOrderType_idName\",\"ExternalName\":null,\"IsLogical\":true,\"IsDataSourceSecret\":false,\"InheritsFrom\":null,\"CreatedOn\":\"2024-12-07T12:55:29Z\",\"ModifiedOn\":\"2024-12-07T12:55:29Z\",\"SourceType\":0,\"AutoNumberFormat\":null,\"Format\":\"Text\",\"ImeMode\":\"Auto\",\"MaxLength\":20,\"YomiOf\":null,\"IsLocalizable\":false,\"DatabaseLength\":40,\"FormulaDefinition\":\"\",\"SourceTypeMask\":0,\"AttributeTypeName\":{\"Value\":\"StringType\"},\"Description\":{\"LocalizedLabels\":[],\"UserLocalizedLabel\":null},\"DisplayName\":{\"LocalizedLabels\":[],\"UserLocalizedLabel\":null},\"IsAuditEnabled\":{\"Value\":true,\"CanBeChanged\":true,\"ManagedPropertyLogicalName\":\"canmodifyauditsettings\"},\"IsGlobalFilterEnabled\":{\"Value\":false,\"CanBeChanged\":true,\"ManagedPropertyLogicalName\":\"canmodifyglobalfiltersettings\"},\"IsSortableEnabled\":{\"Value\":false,\"CanBeChanged\":true,\"ManagedPropertyLogicalName\":\"canmodifyissortablesettings\"},\"IsCustomizable\":{\"Value\":true,\"CanBeChanged\":true,\"ManagedPropertyLogicalName\":\"iscustomizable\"},\"IsRenameable\":{\"Value\":true,\"CanBeChanged\":true,\"ManagedPropertyLogicalName\":\"isrenameable\"},\"IsValidForAdvancedFind\":{\"Value\":false,\"CanBeChanged\":true,\"ManagedPropertyLogicalName\":\"canmodifysearchsettings\"},\"RequiredLevel\":{\"Value\":\"None\",\"CanBeChanged\":true,\"ManagedPropertyLogicalName\":\"canmodifyrequirementlevelsettings\"},\"CanModifyAdditionalSettings\":{\"Value\":true,\"CanBeChanged\":true,\"ManagedPropertyLogicalName\":\"canmodifyadditionalsettings\"},\"Settings\":[],\"FormatName\":{\"Value\":\"Text\"}},{\"@odata.type\":\"#Microsoft.Dynamics.CRM.StringAttributeMetadata\",\"MetadataId\":\"51183353-98b4-ef11-a72f-6045bd0a486c\",\"HasChanged\":null,\"AttributeOf\":null,\"AttributeType\":\"String\",\"ColumnNumber\":11,\"DeprecatedVersion\":null,\"IntroducedVersion\":\"1.0.0.0\",\"EntityLogicalName\":\"mserp_entassetmaintenanceassetservicelevelv2entity\",\"IsCustomAttribute\":true,\"IsPrimaryId\":false,\"IsValidODataAttribute\":true,\"IsPrimaryName\":false,\"IsValidForCreate\":false,\"IsValidForRead\":true,\"IsValidForUpdate\":false,\"CanBeSecuredForRead\":false,\"CanBeSecuredForCreate\":false,\"CanBeSecuredForUpdate\":false,\"IsSecured\":false,\"IsRetrievable\":false,\"IsFilterable\":false,\"IsSearchable\":false,\"IsManaged\":true,\"LinkedAttributeId\":null,\"LogicalName\":\"mserp_formattedservicelevelname\",\"IsValidForForm\":true,\"IsRequiredForForm\":false,\"IsValidForGrid\":true,\"SchemaName\":\"mserp_formattedservicelevelname\",\"ExternalName\":\"FormattedServiceLevelName\",\"IsLogical\":false,\"IsDataSourceSecret\":false,\"InheritsFrom\":null,\"CreatedOn\":\"2024-12-07T12:39:47Z\",\"ModifiedOn\":\"2024-12-07T12:39:47Z\",\"SourceType\":0,\"AutoNumberFormat\":null,\"Format\":\"Text\",\"ImeMode\":\"Auto\",\"MaxLength\":60,\"YomiOf\":null,\"IsLocalizable\":false,\"DatabaseLength\":120,\"FormulaDefinition\":\"\",\"SourceTypeMask\":0,\"AttributeTypeName\":{\"Value\":\"StringType\"},\"Description\":{\"LocalizedLabels\":[],\"UserLocalizedLabel\":null},\"DisplayName\":{\"LocalizedLabels\":[{\"Label\":\"Name\",\"LanguageCode\":1033,\"IsManaged\":true,\"MetadataId\":\"ea254547-e992-4887-b37c-f947cfc0a8ae\",\"HasChanged\":null}],\"UserLocalizedLabel\":{\"Label\":\"Name\",\"LanguageCode\":1033,\"IsManaged\":true,\"MetadataId\":\"ea254547-e992-4887-b37c-f947cfc0a8ae\",\"HasChanged\":null}},\"IsAuditEnabled\":{\"Value\":true,\"CanBeChanged\":true,\"ManagedPropertyLogicalName\":\"canmodifyauditsettings\"},\"IsGlobalFilterEnabled\":{\"Value\":false,\"CanBeChanged\":true,\"ManagedPropertyLogicalName\":\"canmodifyglobalfiltersettings\"},\"IsSortableEnabled\":{\"Value\":false,\"CanBeChanged\":true,\"ManagedPropertyLogicalName\":\"canmodifyissortablesettings\"},\"IsCustomizable\":{\"Value\":true,\"CanBeChanged\":false,\"ManagedPropertyLogicalName\":\"iscustomizable\"},\"IsRenameable\":{\"Value\":true,\"CanBeChanged\":false,\"ManagedPropertyLogicalName\":\"isrenameable\"},\"IsValidForAdvancedFind\":{\"Value\":true,\"CanBeChanged\":true,\"ManagedPropertyLogicalName\":\"canmodifysearchsettings\"},\"RequiredLevel\":{\"Value\":\"None\",\"CanBeChanged\":true,\"ManagedPropertyLogicalName\":\"canmodifyrequirementlevelsettings\"},\"CanModifyAdditionalSettings\":{\"Value\":false,\"CanBeChanged\":false,\"ManagedPropertyLogicalName\":\"canmodifyadditionalsettings\"},\"Settings\":[],\"FormatName\":{\"Value\":\"Text\"}},{\"@odata.type\":\"#Microsoft.Dynamics.CRM.StringAttributeMetadata\",\"MetadataId\":\"50183353-98b4-ef11-a72f-6045bd0a486c\",\"HasChanged\":null,\"AttributeOf\":null,\"AttributeType\":\"String\",\"ColumnNumber\":10,\"DeprecatedVersion\":null,\"IntroducedVersion\":\"1.0.0.0\",\"EntityLogicalName\":\"mserp_entassetmaintenanceassetservicelevelv2entity\",\"IsCustomAttribute\":true,\"IsPrimaryId\":false,\"IsValidODataAttribute\":true,\"IsPrimaryName\":false,\"IsValidForCreate\":true,\"IsValidForRead\":true,\"IsValidForUpdate\":false,\"CanBeSecuredForRead\":false,\"CanBeSecuredForCreate\":false,\"CanBeSecuredForUpdate\":false,\"IsSecured\":false,\"IsRetrievable\":false,\"IsFilterable\":false,\"IsSearchable\":false,\"IsManaged\":true,\"LinkedAttributeId\":null,\"LogicalName\":\"mserp_functionallocationid\",\"IsValidForForm\":true,\"IsRequiredForForm\":false,\"IsValidForGrid\":true,\"SchemaName\":\"mserp_functionallocationid\",\"ExternalName\":\"FunctionalLocationId\",\"IsLogical\":false,\"IsDataSourceSecret\":false,\"InheritsFrom\":null,\"CreatedOn\":\"2024-12-07T12:39:47Z\",\"ModifiedOn\":\"2024-12-07T12:39:47Z\",\"SourceType\":0,\"AutoNumberFormat\":null,\"Format\":\"Text\",\"ImeMode\":\"Auto\",\"MaxLength\":50,\"YomiOf\":null,\"IsLocalizable\":false,\"DatabaseLength\":100,\"FormulaDefinition\":\"\",\"SourceTypeMask\":0,\"AttributeTypeName\":{\"Value\":\"StringType\"},\"Description\":{\"LocalizedLabels\":[],\"UserLocalizedLabel\":null},\"DisplayName\":{\"LocalizedLabels\":[{\"Label\":\"Functional location\",\"LanguageCode\":1033,\"IsManaged\":true,\"MetadataId\":\"4be26716-af28-413b-9fa0-c20b6b3a27fb\",\"HasChanged\":null}],\"UserLocalizedLabel\":{\"Label\":\"Functional location\",\"LanguageCode\":1033,\"IsManaged\":true,\"MetadataId\":\"4be26716-af28-413b-9fa0-c20b6b3a27fb\",\"HasChanged\":null}},\"IsAuditEnabled\":{\"Value\":true,\"CanBeChanged\":true,\"ManagedPropertyLogicalName\":\"canmodifyauditsettings\"},\"IsGlobalFilterEnabled\":{\"Value\":false,\"CanBeChanged\":true,\"ManagedPropertyLogicalName\":\"canmodifyglobalfiltersettings\"},\"IsSortableEnabled\":{\"Value\":false,\"CanBeChanged\":true,\"ManagedPropertyLogicalName\":\"canmodifyissortablesettings\"},\"IsCustomizable\":{\"Value\":true,\"CanBeChanged\":false,\"ManagedPropertyLogicalName\":\"iscustomizable\"},\"IsRenameable\":{\"Value\":true,\"CanBeChanged\":false,\"ManagedPropertyLogicalName\":\"isrenameable\"},\"IsValidForAdvancedFind\":{\"Value\":true,\"CanBeChanged\":true,\"ManagedPropertyLogicalName\":\"canmodifysearchsettings\"},\"RequiredLevel\":{\"Value\":\"None\",\"CanBeChanged\":true,\"ManagedPropertyLogicalName\":\"canmodifyrequirementlevelsettings\"},\"CanModifyAdditionalSettings\":{\"Value\":false,\"CanBeChanged\":false,\"ManagedPropertyLogicalName\":\"canmodifyadditionalsettings\"},\"Settings\":[],\"FormatName\":{\"Value\":\"Text\"}},{\"@odata.type\":\"#Microsoft.Dynamics.CRM.StringAttributeMetadata\",\"MetadataId\":\"4a183353-98b4-ef11-a72f-6045bd0a486c\",\"HasChanged\":null,\"AttributeOf\":null,\"AttributeType\":\"String\",\"ColumnNumber\":4,\"DeprecatedVersion\":null,\"IntroducedVersion\":\"1.0.0.0\",\"EntityLogicalName\":\"mserp_entassetmaintenanceassetservicelevelv2entity\",\"IsCustomAttribute\":true,\"IsPrimaryId\":false,\"IsValidODataAttribute\":true,\"IsPrimaryName\":false,\"IsValidForCreate\":true,\"IsValidForRead\":true,\"IsValidForUpdate\":false,\"CanBeSecuredForRead\":false,\"CanBeSecuredForCreate\":false,\"CanBeSecuredForUpdate\":false,\"IsSecured\":false,\"IsRetrievable\":false,\"IsFilterable\":false,\"IsSearchable\":false,\"IsManaged\":true,\"LinkedAttributeId\":null,\"LogicalName\":\"mserp_maintenanceassetid\",\"IsValidForForm\":true,\"IsRequiredForForm\":false,\"IsValidForGrid\":true,\"SchemaName\":\"mserp_maintenanceassetid\",\"ExternalName\":\"MaintenanceAssetId\",\"IsLogical\":false,\"IsDataSourceSecret\":false,\"InheritsFrom\":null,\"CreatedOn\":\"2024-12-07T12:39:47Z\",\"ModifiedOn\":\"2024-12-07T12:39:47Z\",\"SourceType\":0,\"AutoNumberFormat\":null,\"Format\":\"Text\",\"ImeMode\":\"Auto\",\"MaxLength\":50,\"YomiOf\":null,\"IsLocalizable\":false,\"DatabaseLength\":100,\"FormulaDefinition\":\"\",\"SourceTypeMask\":0,\"AttributeTypeName\":{\"Value\":\"StringType\"},\"Description\":{\"LocalizedLabels\":[],\"UserLocalizedLabel\":null},\"DisplayName\":{\"LocalizedLabels\":[{\"Label\":\"Asset\",\"LanguageCode\":1033,\"IsManaged\":true,\"MetadataId\":\"29011bbf-d877-4645-94f6-accdc569c392\",\"HasChanged\":null}],\"UserLocalizedLabel\":{\"Label\":\"Asset\",\"LanguageCode\":1033,\"IsManaged\":true,\"MetadataId\":\"29011bbf-d877-4645-94f6-accdc569c392\",\"HasChanged\":null}},\"IsAuditEnabled\":{\"Value\":true,\"CanBeChanged\":true,\"ManagedPropertyLogicalName\":\"canmodifyauditsettings\"},\"IsGlobalFilterEnabled\":{\"Value\":false,\"CanBeChanged\":true,\"ManagedPropertyLogicalName\":\"canmodifyglobalfiltersettings\"},\"IsSortableEnabled\":{\"Value\":false,\"CanBeChanged\":true,\"ManagedPropertyLogicalName\":\"canmodifyissortablesettings\"},\"IsCustomizable\":{\"Value\":true,\"CanBeChanged\":false,\"ManagedPropertyLogicalName\":\"iscustomizable\"},\"IsRenameable\":{\"Value\":true,\"CanBeChanged\":false,\"ManagedPropertyLogicalName\":\"isrenameable\"},\"IsValidForAdvancedFind\":{\"Value\":true,\"CanBeChanged\":true,\"ManagedPropertyLogicalName\":\"canmodifysearchsettings\"},\"RequiredLevel\":{\"Value\":\"None\",\"CanBeChanged\":true,\"ManagedPropertyLogicalName\":\"canmodifyrequirementlevelsettings\"},\"CanModifyAdditionalSettings\":{\"Value\":false,\"CanBeChanged\":false,\"ManagedPropertyLogicalName\":\"canmodifyadditionalsettings\"},\"Settings\":[],\"FormatName\":{\"Value\":\"Text\"}},{\"@odata.type\":\"#Microsoft.Dynamics.CRM.StringAttributeMetadata\",\"MetadataId\":\"4d183353-98b4-ef11-a72f-6045bd0a486c\",\"HasChanged\":null,\"AttributeOf\":null,\"AttributeType\":\"String\",\"ColumnNumber\":7,\"DeprecatedVersion\":null,\"IntroducedVersion\":\"1.0.0.0\",\"EntityLogicalName\":\"mserp_entassetmaintenanceassetservicelevelv2entity\",\"IsCustomAttribute\":true,\"IsPrimaryId\":false,\"IsValidODataAttribute\":true,\"IsPrimaryName\":false,\"IsValidForCreate\":true,\"IsValidForRead\":true,\"IsValidForUpdate\":false,\"CanBeSecuredForRead\":false,\"CanBeSecuredForCreate\":false,\"CanBeSecuredForUpdate\":false,\"IsSecured\":false,\"IsRetrievable\":false,\"IsFilterable\":false,\"IsSearchable\":false,\"IsManaged\":true,\"LinkedAttributeId\":null,\"LogicalName\":\"mserp_maintenanceassettypeid\",\"IsValidForForm\":true,\"IsRequiredForForm\":false,\"IsValidForGrid\":true,\"SchemaName\":\"mserp_maintenanceassettypeid\",\"ExternalName\":\"MaintenanceAssetTypeId\",\"IsLogical\":false,\"IsDataSourceSecret\":false,\"InheritsFrom\":null,\"CreatedOn\":\"2024-12-07T12:39:47Z\",\"ModifiedOn\":\"2024-12-07T12:39:47Z\",\"SourceType\":0,\"AutoNumberFormat\":null,\"Format\":\"Text\",\"ImeMode\":\"Auto\",\"MaxLength\":20,\"YomiOf\":null,\"IsLocalizable\":false,\"DatabaseLength\":40,\"FormulaDefinition\":\"\",\"SourceTypeMask\":0,\"AttributeTypeName\":{\"Value\":\"StringType\"},\"Description\":{\"LocalizedLabels\":[],\"UserLocalizedLabel\":null},\"DisplayName\":{\"LocalizedLabels\":[{\"Label\":\"Asset type\",\"LanguageCode\":1033,\"IsManaged\":true,\"MetadataId\":\"20e57b77-aa47-4fbe-9f3a-1824e3c4f5ef\",\"HasChanged\":null}],\"UserLocalizedLabel\":{\"Label\":\"Asset type\",\"LanguageCode\":1033,\"IsManaged\":true,\"MetadataId\":\"20e57b77-aa47-4fbe-9f3a-1824e3c4f5ef\",\"HasChanged\":null}},\"IsAuditEnabled\":{\"Value\":true,\"CanBeChanged\":true,\"ManagedPropertyLogicalName\":\"canmodifyauditsettings\"},\"IsGlobalFilterEnabled\":{\"Value\":false,\"CanBeChanged\":true,\"ManagedPropertyLogicalName\":\"canmodifyglobalfiltersettings\"},\"IsSortableEnabled\":{\"Value\":false,\"CanBeChanged\":true,\"ManagedPropertyLogicalName\":\"canmodifyissortablesettings\"},\"IsCustomizable\":{\"Value\":true,\"CanBeChanged\":false,\"ManagedPropertyLogicalName\":\"iscustomizable\"},\"IsRenameable\":{\"Value\":true,\"CanBeChanged\":false,\"ManagedPropertyLogicalName\":\"isrenameable\"},\"IsValidForAdvancedFind\":{\"Value\":true,\"CanBeChanged\":true,\"ManagedPropertyLogicalName\":\"canmodifysearchsettings\"},\"RequiredLevel\":{\"Value\":\"None\",\"CanBeChanged\":true,\"ManagedPropertyLogicalName\":\"canmodifyrequirementlevelsettings\"},\"CanModifyAdditionalSettings\":{\"Value\":false,\"CanBeChanged\":false,\"ManagedPropertyLogicalName\":\"canmodifyadditionalsettings\"},\"Settings\":[],\"FormatName\":{\"Value\":\"Text\"}},{\"@odata.type\":\"#Microsoft.Dynamics.CRM.StringAttributeMetadata\",\"MetadataId\":\"4b183353-98b4-ef11-a72f-6045bd0a486c\",\"HasChanged\":null,\"AttributeOf\":null,\"AttributeType\":\"String\",\"ColumnNumber\":5,\"DeprecatedVersion\":null,\"IntroducedVersion\":\"1.0.0.0\",\"EntityLogicalName\":\"mserp_entassetmaintenanceassetservicelevelv2entity\",\"IsCustomAttribute\":true,\"IsPrimaryId\":false,\"IsValidODataAttribute\":true,\"IsPrimaryName\":false,\"IsValidForCreate\":true,\"IsValidForRead\":true,\"IsValidForUpdate\":false,\"CanBeSecuredForRead\":false,\"CanBeSecuredForCreate\":false,\"CanBeSecuredForUpdate\":false,\"IsSecured\":false,\"IsRetrievable\":false,\"IsFilterable\":false,\"IsSearchable\":false,\"IsManaged\":true,\"LinkedAttributeId\":null,\"LogicalName\":\"mserp_modelid\",\"IsValidForForm\":true,\"IsRequiredForForm\":false,\"IsValidForGrid\":true,\"SchemaName\":\"mserp_modelid\",\"ExternalName\":\"ModelId\",\"IsLogical\":false,\"IsDataSourceSecret\":false,\"InheritsFrom\":null,\"CreatedOn\":\"2024-12-07T12:39:47Z\",\"ModifiedOn\":\"2024-12-07T12:39:47Z\",\"SourceType\":0,\"AutoNumberFormat\":null,\"Format\":\"Text\",\"ImeMode\":\"Auto\",\"MaxLength\":20,\"YomiOf\":null,\"IsLocalizable\":false,\"DatabaseLength\":40,\"FormulaDefinition\":\"\",\"SourceTypeMask\":0,\"AttributeTypeName\":{\"Value\":\"StringType\"},\"Description\":{\"LocalizedLabels\":[],\"UserLocalizedLabel\":null},\"DisplayName\":{\"LocalizedLabels\":[{\"Label\":\"Model\",\"LanguageCode\":1033,\"IsManaged\":true,\"MetadataId\":\"0ea9b1ce-75b9-4438-8c53-815d46b23dd9\",\"HasChanged\":null}],\"UserLocalizedLabel\":{\"Label\":\"Model\",\"LanguageCode\":1033,\"IsManaged\":true,\"MetadataId\":\"0ea9b1ce-75b9-4438-8c53-815d46b23dd9\",\"HasChanged\":null}},\"IsAuditEnabled\":{\"Value\":true,\"CanBeChanged\":true,\"ManagedPropertyLogicalName\":\"canmodifyauditsettings\"},\"IsGlobalFilterEnabled\":{\"Value\":false,\"CanBeChanged\":true,\"ManagedPropertyLogicalName\":\"canmodifyglobalfiltersettings\"},\"IsSortableEnabled\":{\"Value\":false,\"CanBeChanged\":true,\"ManagedPropertyLogicalName\":\"canmodifyissortablesettings\"},\"IsCustomizable\":{\"Value\":true,\"CanBeChanged\":false,\"ManagedPropertyLogicalName\":\"iscustomizable\"},\"IsRenameable\":{\"Value\":true,\"CanBeChanged\":false,\"ManagedPropertyLogicalName\":\"isrenameable\"},\"IsValidForAdvancedFind\":{\"Value\":true,\"CanBeChanged\":true,\"ManagedPropertyLogicalName\":\"canmodifysearchsettings\"},\"RequiredLevel\":{\"Value\":\"None\",\"CanBeChanged\":true,\"ManagedPropertyLogicalName\":\"canmodifyrequirementlevelsettings\"},\"CanModifyAdditionalSettings\":{\"Value\":false,\"CanBeChanged\":false,\"ManagedPropertyLogicalName\":\"canmodifyadditionalsettings\"},\"Settings\":[],\"FormatName\":{\"Value\":\"Text\"}},{\"@odata.type\":\"#Microsoft.Dynamics.CRM.StringAttributeMetadata\",\"MetadataId\":\"4c183353-98b4-ef11-a72f-6045bd0a486c\",\"HasChanged\":null,\"AttributeOf\":null,\"AttributeType\":\"String\",\"ColumnNumber\":6,\"DeprecatedVersion\":null,\"IntroducedVersion\":\"1.0.0.0\",\"EntityLogicalName\":\"mserp_entassetmaintenanceassetservicelevelv2entity\",\"IsCustomAttribute\":true,\"IsPrimaryId\":false,\"IsValidODataAttribute\":true,\"IsPrimaryName\":false,\"IsValidForCreate\":true,\"IsValidForRead\":true,\"IsValidForUpdate\":false,\"CanBeSecuredForRead\":false,\"CanBeSecuredForCreate\":false,\"CanBeSecuredForUpdate\":false,\"IsSecured\":false,\"IsRetrievable\":false,\"IsFilterable\":false,\"IsSearchable\":false,\"IsManaged\":true,\"LinkedAttributeId\":null,\"LogicalName\":\"mserp_modelproductid\",\"IsValidForForm\":true,\"IsRequiredForForm\":false,\"IsValidForGrid\":true,\"SchemaName\":\"mserp_modelproductid\",\"ExternalName\":\"ModelProductId\",\"IsLogical\":false,\"IsDataSourceSecret\":false,\"InheritsFrom\":null,\"CreatedOn\":\"2024-12-07T12:39:47Z\",\"ModifiedOn\":\"2024-12-07T12:39:47Z\",\"SourceType\":0,\"AutoNumberFormat\":null,\"Format\":\"Text\",\"ImeMode\":\"Auto\",\"MaxLength\":20,\"YomiOf\":null,\"IsLocalizable\":false,\"DatabaseLength\":40,\"FormulaDefinition\":\"\",\"SourceTypeMask\":0,\"AttributeTypeName\":{\"Value\":\"StringType\"},\"Description\":{\"LocalizedLabels\":[],\"UserLocalizedLabel\":null},\"DisplayName\":{\"LocalizedLabels\":[{\"Label\":\"Manufacturer\",\"LanguageCode\":1033,\"IsManaged\":true,\"MetadataId\":\"c2080ed4-f30f-449a-bd22-14949f54df1a\",\"HasChanged\":null}],\"UserLocalizedLabel\":{\"Label\":\"Manufacturer\",\"LanguageCode\":1033,\"IsManaged\":true,\"MetadataId\":\"c2080ed4-f30f-449a-bd22-14949f54df1a\",\"HasChanged\":null}},\"IsAuditEnabled\":{\"Value\":true,\"CanBeChanged\":true,\"ManagedPropertyLogicalName\":\"canmodifyauditsettings\"},\"IsGlobalFilterEnabled\":{\"Value\":false,\"CanBeChanged\":true,\"ManagedPropertyLogicalName\":\"canmodifyglobalfiltersettings\"},\"IsSortableEnabled\":{\"Value\":false,\"CanBeChanged\":true,\"ManagedPropertyLogicalName\":\"canmodifyissortablesettings\"},\"IsCustomizable\":{\"Value\":true,\"CanBeChanged\":false,\"ManagedPropertyLogicalName\":\"iscustomizable\"},\"IsRenameable\":{\"Value\":true,\"CanBeChanged\":false,\"ManagedPropertyLogicalName\":\"isrenameable\"},\"IsValidForAdvancedFind\":{\"Value\":true,\"CanBeChanged\":true,\"ManagedPropertyLogicalName\":\"canmodifysearchsettings\"},\"RequiredLevel\":{\"Value\":\"None\",\"CanBeChanged\":true,\"ManagedPropertyLogicalName\":\"canmodifyrequirementlevelsettings\"},\"CanModifyAdditionalSettings\":{\"Value\":false,\"CanBeChanged\":false,\"ManagedPropertyLogicalName\":\"canmodifyadditionalsettings\"},\"Settings\":[],\"FormatName\":{\"Value\":\"Text\"}},{\"@odata.type\":\"#Microsoft.Dynamics.CRM.StringAttributeMetadata\",\"MetadataId\":\"48183353-98b4-ef11-a72f-6045bd0a486c\",\"HasChanged\":null,\"AttributeOf\":null,\"AttributeType\":\"String\",\"ColumnNumber\":2,\"DeprecatedVersion\":null,\"IntroducedVersion\":\"1.0.0.0\",\"EntityLogicalName\":\"mserp_entassetmaintenanceassetservicelevelv2entity\",\"IsCustomAttribute\":true,\"IsPrimaryId\":false,\"IsValidODataAttribute\":true,\"IsPrimaryName\":true,\"IsValidForCreate\":true,\"IsValidForRead\":true,\"IsValidForUpdate\":true,\"CanBeSecuredForRead\":false,\"CanBeSecuredForCreate\":false,\"CanBeSecuredForUpdate\":false,\"IsSecured\":false,\"IsRetrievable\":true,\"IsFilterable\":false,\"IsSearchable\":true,\"IsManaged\":true,\"LinkedAttributeId\":null,\"LogicalName\":\"mserp_primaryfield\",\"IsValidForForm\":true,\"IsRequiredForForm\":true,\"IsValidForGrid\":true,\"SchemaName\":\"mserp_primaryfield\",\"ExternalName\":\"PlaceholderName\",\"IsLogical\":false,\"IsDataSourceSecret\":false,\"InheritsFrom\":null,\"CreatedOn\":\"2024-12-07T12:39:47Z\",\"ModifiedOn\":\"2024-12-07T12:39:47Z\",\"SourceType\":0,\"AutoNumberFormat\":null,\"Format\":\"Text\",\"ImeMode\":\"Auto\",\"MaxLength\":256,\"YomiOf\":null,\"IsLocalizable\":false,\"DatabaseLength\":512,\"FormulaDefinition\":\"\",\"SourceTypeMask\":0,\"AttributeTypeName\":{\"Value\":\"StringType\"},\"Description\":{\"LocalizedLabels\":[],\"UserLocalizedLabel\":null},\"DisplayName\":{\"LocalizedLabels\":[{\"Label\":\"Primary Field\",\"LanguageCode\":1033,\"IsManaged\":true,\"MetadataId\":\"47b82117-b713-4357-8ae4-f00d255e3464\",\"HasChanged\":null}],\"UserLocalizedLabel\":{\"Label\":\"Primary Field\",\"LanguageCode\":1033,\"IsManaged\":true,\"MetadataId\":\"47b82117-b713-4357-8ae4-f00d255e3464\",\"HasChanged\":null}},\"IsAuditEnabled\":{\"Value\":true,\"CanBeChanged\":true,\"ManagedPropertyLogicalName\":\"canmodifyauditsettings\"},\"IsGlobalFilterEnabled\":{\"Value\":false,\"CanBeChanged\":true,\"ManagedPropertyLogicalName\":\"canmodifyglobalfiltersettings\"},\"IsSortableEnabled\":{\"Value\":false,\"CanBeChanged\":true,\"ManagedPropertyLogicalName\":\"canmodifyissortablesettings\"},\"IsCustomizable\":{\"Value\":true,\"CanBeChanged\":false,\"ManagedPropertyLogicalName\":\"iscustomizable\"},\"IsRenameable\":{\"Value\":true,\"CanBeChanged\":false,\"ManagedPropertyLogicalName\":\"isrenameable\"},\"IsValidForAdvancedFind\":{\"Value\":true,\"CanBeChanged\":true,\"ManagedPropertyLogicalName\":\"canmodifysearchsettings\"},\"RequiredLevel\":{\"Value\":\"None\",\"CanBeChanged\":true,\"ManagedPropertyLogicalName\":\"canmodifyrequirementlevelsettings\"},\"CanModifyAdditionalSettings\":{\"Value\":true,\"CanBeChanged\":false,\"ManagedPropertyLogicalName\":\"canmodifyadditionalsettings\"},\"Settings\":[],\"FormatName\":{\"Value\":\"Text\"}},{\"@odata.type\":\"#Microsoft.Dynamics.CRM.StringAttributeMetadata\",\"MetadataId\":\"4e183353-98b4-ef11-a72f-6045bd0a486c\",\"HasChanged\":null,\"AttributeOf\":null,\"AttributeType\":\"String\",\"ColumnNumber\":8,\"DeprecatedVersion\":null,\"IntroducedVersion\":\"1.0.0.0\",\"EntityLogicalName\":\"mserp_entassetmaintenanceassetservicelevelv2entity\",\"IsCustomAttribute\":true,\"IsPrimaryId\":false,\"IsValidODataAttribute\":true,\"IsPrimaryName\":false,\"IsValidForCreate\":true,\"IsValidForRead\":true,\"IsValidForUpdate\":false,\"CanBeSecuredForRead\":false,\"CanBeSecuredForCreate\":false,\"CanBeSecuredForUpdate\":false,\"IsSecured\":false,\"IsRetrievable\":false,\"IsFilterable\":false,\"IsSearchable\":false,\"IsManaged\":true,\"LinkedAttributeId\":null,\"LogicalName\":\"mserp_productid\",\"IsValidForForm\":true,\"IsRequiredForForm\":false,\"IsValidForGrid\":true,\"SchemaName\":\"mserp_productid\",\"ExternalName\":\"ProductId\",\"IsLogical\":false,\"IsDataSourceSecret\":false,\"InheritsFrom\":null,\"CreatedOn\":\"2024-12-07T12:39:47Z\",\"ModifiedOn\":\"2024-12-07T12:39:47Z\",\"SourceType\":0,\"AutoNumberFormat\":null,\"Format\":\"Text\",\"ImeMode\":\"Auto\",\"MaxLength\":20,\"YomiOf\":null,\"IsLocalizable\":false,\"DatabaseLength\":40,\"FormulaDefinition\":\"\",\"SourceTypeMask\":0,\"AttributeTypeName\":{\"Value\":\"StringType\"},\"Description\":{\"LocalizedLabels\":[],\"UserLocalizedLabel\":null},\"DisplayName\":{\"LocalizedLabels\":[{\"Label\":\"Manufacturer\",\"LanguageCode\":1033,\"IsManaged\":true,\"MetadataId\":\"ec511395-a289-48a7-abbe-eafaf25ab62d\",\"HasChanged\":null}],\"UserLocalizedLabel\":{\"Label\":\"Manufacturer\",\"LanguageCode\":1033,\"IsManaged\":true,\"MetadataId\":\"ec511395-a289-48a7-abbe-eafaf25ab62d\",\"HasChanged\":null}},\"IsAuditEnabled\":{\"Value\":true,\"CanBeChanged\":true,\"ManagedPropertyLogicalName\":\"canmodifyauditsettings\"},\"IsGlobalFilterEnabled\":{\"Value\":false,\"CanBeChanged\":true,\"ManagedPropertyLogicalName\":\"canmodifyglobalfiltersettings\"},\"IsSortableEnabled\":{\"Value\":false,\"CanBeChanged\":true,\"ManagedPropertyLogicalName\":\"canmodifyissortablesettings\"},\"IsCustomizable\":{\"Value\":true,\"CanBeChanged\":false,\"ManagedPropertyLogicalName\":\"iscustomizable\"},\"IsRenameable\":{\"Value\":true,\"CanBeChanged\":false,\"ManagedPropertyLogicalName\":\"isrenameable\"},\"IsValidForAdvancedFind\":{\"Value\":true,\"CanBeChanged\":true,\"ManagedPropertyLogicalName\":\"canmodifysearchsettings\"},\"RequiredLevel\":{\"Value\":\"None\",\"CanBeChanged\":true,\"ManagedPropertyLogicalName\":\"canmodifyrequirementlevelsettings\"},\"CanModifyAdditionalSettings\":{\"Value\":false,\"CanBeChanged\":false,\"ManagedPropertyLogicalName\":\"canmodifyadditionalsettings\"},\"Settings\":[],\"FormatName\":{\"Value\":\"Text\"}},{\"@odata.type\":\"#Microsoft.Dynamics.CRM.IntegerAttributeMetadata\",\"MetadataId\":\"49183353-98b4-ef11-a72f-6045bd0a486c\",\"HasChanged\":null,\"AttributeOf\":null,\"AttributeType\":\"Integer\",\"ColumnNumber\":3,\"DeprecatedVersion\":null,\"IntroducedVersion\":\"1.0.0.0\",\"EntityLogicalName\":\"mserp_entassetmaintenanceassetservicelevelv2entity\",\"IsCustomAttribute\":true,\"IsPrimaryId\":false,\"IsValidODataAttribute\":true,\"IsPrimaryName\":false,\"IsValidForCreate\":true,\"IsValidForRead\":true,\"IsValidForUpdate\":false,\"CanBeSecuredForRead\":false,\"CanBeSecuredForCreate\":false,\"CanBeSecuredForUpdate\":false,\"IsSecured\":false,\"IsRetrievable\":false,\"IsFilterable\":false,\"IsSearchable\":false,\"IsManaged\":true,\"LinkedAttributeId\":null,\"LogicalName\":\"mserp_servicelevel\",\"IsValidForForm\":true,\"IsRequiredForForm\":false,\"IsValidForGrid\":true,\"SchemaName\":\"mserp_servicelevel\",\"ExternalName\":\"ServiceLevel\",\"IsLogical\":false,\"IsDataSourceSecret\":false,\"InheritsFrom\":null,\"CreatedOn\":\"2024-12-07T12:39:47Z\",\"ModifiedOn\":\"2024-12-07T12:39:47Z\",\"SourceType\":0,\"AutoNumberFormat\":null,\"Format\":\"None\",\"MaxValue\":2147483647,\"MinValue\":-2147483648,\"FormulaDefinition\":\"\",\"SourceTypeMask\":0,\"AttributeTypeName\":{\"Value\":\"IntegerType\"},\"Description\":{\"LocalizedLabels\":[],\"UserLocalizedLabel\":null},\"DisplayName\":{\"LocalizedLabels\":[{\"Label\":\"Service level\",\"LanguageCode\":1033,\"IsManaged\":true,\"MetadataId\":\"61369594-1e27-4b71-96e7-4688282978a4\",\"HasChanged\":null}],\"UserLocalizedLabel\":{\"Label\":\"Service level\",\"LanguageCode\":1033,\"IsManaged\":true,\"MetadataId\":\"61369594-1e27-4b71-96e7-4688282978a4\",\"HasChanged\":null}},\"IsAuditEnabled\":{\"Value\":true,\"CanBeChanged\":true,\"ManagedPropertyLogicalName\":\"canmodifyauditsettings\"},\"IsGlobalFilterEnabled\":{\"Value\":false,\"CanBeChanged\":true,\"ManagedPropertyLogicalName\":\"canmodifyglobalfiltersettings\"},\"IsSortableEnabled\":{\"Value\":false,\"CanBeChanged\":true,\"ManagedPropertyLogicalName\":\"canmodifyissortablesettings\"},\"IsCustomizable\":{\"Value\":true,\"CanBeChanged\":false,\"ManagedPropertyLogicalName\":\"iscustomizable\"},\"IsRenameable\":{\"Value\":true,\"CanBeChanged\":false,\"ManagedPropertyLogicalName\":\"isrenameable\"},\"IsValidForAdvancedFind\":{\"Value\":true,\"CanBeChanged\":true,\"ManagedPropertyLogicalName\":\"canmodifysearchsettings\"},\"RequiredLevel\":{\"Value\":\"ApplicationRequired\",\"CanBeChanged\":true,\"ManagedPropertyLogicalName\":\"canmodifyrequirementlevelsettings\"},\"CanModifyAdditionalSettings\":{\"Value\":false,\"CanBeChanged\":false,\"ManagedPropertyLogicalName\":\"canmodifyadditionalsettings\"},\"Settings\":[]},{\"@odata.type\":\"#Microsoft.Dynamics.CRM.StringAttributeMetadata\",\"MetadataId\":\"4f183353-98b4-ef11-a72f-6045bd0a486c\",\"HasChanged\":null,\"AttributeOf\":null,\"AttributeType\":\"String\",\"ColumnNumber\":9,\"DeprecatedVersion\":null,\"IntroducedVersion\":\"1.0.0.0\",\"EntityLogicalName\":\"mserp_entassetmaintenanceassetservicelevelv2entity\",\"IsCustomAttribute\":true,\"IsPrimaryId\":false,\"IsValidODataAttribute\":true,\"IsPrimaryName\":false,\"IsValidForCreate\":true,\"IsValidForRead\":true,\"IsValidForUpdate\":false,\"CanBeSecuredForRead\":false,\"CanBeSecuredForCreate\":false,\"CanBeSecuredForUpdate\":false,\"IsSecured\":false,\"IsRetrievable\":false,\"IsFilterable\":false,\"IsSearchable\":false,\"IsManaged\":true,\"LinkedAttributeId\":null,\"LogicalName\":\"mserp_workordertypeid\",\"IsValidForForm\":true,\"IsRequiredForForm\":false,\"IsValidForGrid\":true,\"SchemaName\":\"mserp_workordertypeid\",\"ExternalName\":\"WorkOrderTypeId\",\"IsLogical\":false,\"IsDataSourceSecret\":false,\"InheritsFrom\":null,\"CreatedOn\":\"2024-12-07T12:39:47Z\",\"ModifiedOn\":\"2024-12-07T12:39:47Z\",\"SourceType\":0,\"AutoNumberFormat\":null,\"Format\":\"Text\",\"ImeMode\":\"Auto\",\"MaxLength\":20,\"YomiOf\":null,\"IsLocalizable\":false,\"DatabaseLength\":40,\"FormulaDefinition\":\"\",\"SourceTypeMask\":0,\"AttributeTypeName\":{\"Value\":\"StringType\"},\"Description\":{\"LocalizedLabels\":[],\"UserLocalizedLabel\":null},\"DisplayName\":{\"LocalizedLabels\":[{\"Label\":\"Work order type\",\"LanguageCode\":1033,\"IsManaged\":true,\"MetadataId\":\"9ef9233b-4621-4660-ab39-c4dead22cad2\",\"HasChanged\":null}],\"UserLocalizedLabel\":{\"Label\":\"Work order type\",\"LanguageCode\":1033,\"IsManaged\":true,\"MetadataId\":\"9ef9233b-4621-4660-ab39-c4dead22cad2\",\"HasChanged\":null}},\"IsAuditEnabled\":{\"Value\":true,\"CanBeChanged\":true,\"ManagedPropertyLogicalName\":\"canmodifyauditsettings\"},\"IsGlobalFilterEnabled\":{\"Value\":false,\"CanBeChanged\":true,\"ManagedPropertyLogicalName\":\"canmodifyglobalfiltersettings\"},\"IsSortableEnabled\":{\"Value\":false,\"CanBeChanged\":true,\"ManagedPropertyLogicalName\":\"canmodifyissortablesettings\"},\"IsCustomizable\":{\"Value\":true,\"CanBeChanged\":false,\"ManagedPropertyLogicalName\":\"iscustomizable\"},\"IsRenameable\":{\"Value\":true,\"CanBeChanged\":false,\"ManagedPropertyLogicalName\":\"isrenameable\"},\"IsValidForAdvancedFind\":{\"Value\":true,\"CanBeChanged\":true,\"ManagedPropertyLogicalName\":\"canmodifysearchsettings\"},\"RequiredLevel\":{\"Value\":\"None\",\"CanBeChanged\":true,\"ManagedPropertyLogicalName\":\"canmodifyrequirementlevelsettings\"},\"CanModifyAdditionalSettings\":{\"Value\":false,\"CanBeChanged\":false,\"ManagedPropertyLogicalName\":\"canmodifyadditionalsettings\"},\"Settings\":[],\"FormatName\":{\"Value\":\"Text\"}}],\"ManyToOneRelationships\":[{\"MetadataId\":\"cb183353-98b4-ef11-a72f-6045bd0a486c\",\"HasChanged\":null,\"IsCustomRelationship\":true,\"IsValidForAdvancedFind\":true,\"SchemaName\":\"mserp_EntAssetMaintenanceAssetServiceLevelV2Entity_dataAreaId_rel\",\"SecurityTypes\":\"Append\",\"IsManaged\":true,\"RelationshipType\":\"OneToManyRelationship\",\"IntroducedVersion\":\"1.0.0.0\",\"ReferencedAttribute\":\"cdm_companyid\",\"ReferencedEntity\":\"cdm_company\",\"ReferencingAttribute\":\"mserp_dataareaid_id\",\"ReferencingEntity\":\"mserp_entassetmaintenanceassetservicelevelv2entity\",\"IsHierarchical\":false,\"EntityKey\":null,\"IsRelationshipAttributeDenormalized\":false,\"ReferencedEntityNavigationPropertyName\":\"mserp_EntAssetMaintenanceAssetServiceLevelV2Entity_dataAreaId_rel\",\"ReferencingEntityNavigationPropertyName\":\"mserp_dataAreaId_id\",\"RelationshipBehavior\":1,\"IsDenormalizedLookup\":null,\"DenormalizedAttributeName\":null,\"IsCustomizable\":{\"Value\":true,\"CanBeChanged\":false,\"ManagedPropertyLogicalName\":\"iscustomizable\"},\"AssociatedMenuConfiguration\":{\"Behavior\":\"UseCollectionName\",\"Group\":\"Details\",\"Order\":10000,\"IsCustomizable\":true,\"Icon\":null,\"ViewId\":\"00000000-0000-0000-0000-000000000000\",\"AvailableOffline\":true,\"MenuId\":null,\"QueryApi\":null,\"Label\":{\"LocalizedLabels\":[],\"UserLocalizedLabel\":null}},\"CascadeConfiguration\":{\"Assign\":\"NoCascade\",\"Delete\":\"NoCascade\",\"Archive\":\"RemoveLink\",\"Merge\":\"NoCascade\",\"Reparent\":\"NoCascade\",\"Share\":\"NoCascade\",\"Unshare\":\"NoCascade\",\"RollupView\":\"NoCascade\"},\"RelationshipAttributes\":[]},{\"MetadataId\":\"531cc35e-98b4-ef11-a72f-6045bd0a486c\",\"HasChanged\":null,\"IsCustomRelationship\":true,\"IsValidForAdvancedFind\":true,\"SchemaName\":\"mserp_FK_EntAssetMaintenanceAssetServiceLevelV2Entity_MaintenanceAsset\",\"SecurityTypes\":\"Append\",\"IsManaged\":true,\"RelationshipType\":\"OneToManyRelationship\",\"IntroducedVersion\":\"1.0.0.0\",\"ReferencedAttribute\":\"mserp_entassetmaintenanceassetv3entityid\",\"ReferencedEntity\":\"mserp_entassetmaintenanceassetv3entity\",\"ReferencingAttribute\":\"mserp_fk_maintenanceasset_id\",\"ReferencingEntity\":\"mserp_entassetmaintenanceassetservicelevelv2entity\",\"IsHierarchical\":false,\"EntityKey\":null,\"IsRelationshipAttributeDenormalized\":false,\"ReferencedEntityNavigationPropertyName\":\"mserp_FK_EntAssetMaintenanceAssetServiceLevelV2Entity_MaintenanceAsset\",\"ReferencingEntityNavigationPropertyName\":\"mserp_FK_MaintenanceAsset_id\",\"RelationshipBehavior\":1,\"IsDenormalizedLookup\":null,\"DenormalizedAttributeName\":null,\"IsCustomizable\":{\"Value\":true,\"CanBeChanged\":false,\"ManagedPropertyLogicalName\":\"iscustomizable\"},\"AssociatedMenuConfiguration\":{\"Behavior\":\"UseCollectionName\",\"Group\":\"Details\",\"Order\":10000,\"IsCustomizable\":true,\"Icon\":null,\"ViewId\":\"00000000-0000-0000-0000-000000000000\",\"AvailableOffline\":true,\"MenuId\":null,\"QueryApi\":null,\"Label\":{\"LocalizedLabels\":[],\"UserLocalizedLabel\":null}},\"CascadeConfiguration\":{\"Assign\":\"NoCascade\",\"Delete\":\"NoCascade\",\"Archive\":\"RemoveLink\",\"Merge\":\"NoCascade\",\"Reparent\":\"NoCascade\",\"Share\":\"NoCascade\",\"Unshare\":\"NoCascade\",\"RollupView\":\"NoCascade\"},\"RelationshipAttributes\":[]},{\"MetadataId\":\"26e6d26c-98b4-ef11-a72f-6045bd0a486c\",\"HasChanged\":null,\"IsCustomRelationship\":true,\"IsValidForAdvancedFind\":true,\"SchemaName\":\"mserp_FK_EntAssetMaintenanceAssetServiceLevelV2Entity_Model\",\"SecurityTypes\":\"Append\",\"IsManaged\":true,\"RelationshipType\":\"OneToManyRelationship\",\"IntroducedVersion\":\"1.0.0.0\",\"ReferencedAttribute\":\"mserp_entassetmaintenancemodelentityid\",\"ReferencedEntity\":\"mserp_entassetmaintenancemodelentity\",\"ReferencingAttribute\":\"mserp_fk_model_id\",\"ReferencingEntity\":\"mserp_entassetmaintenanceassetservicelevelv2entity\",\"IsHierarchical\":false,\"EntityKey\":null,\"IsRelationshipAttributeDenormalized\":false,\"ReferencedEntityNavigationPropertyName\":\"mserp_FK_EntAssetMaintenanceAssetServiceLevelV2Entity_Model\",\"ReferencingEntityNavigationPropertyName\":\"mserp_FK_Model_id\",\"RelationshipBehavior\":1,\"IsDenormalizedLookup\":null,\"DenormalizedAttributeName\":null,\"IsCustomizable\":{\"Value\":true,\"CanBeChanged\":false,\"ManagedPropertyLogicalName\":\"iscustomizable\"},\"AssociatedMenuConfiguration\":{\"Behavior\":\"UseCollectionName\",\"Group\":\"Details\",\"Order\":10000,\"IsCustomizable\":true,\"Icon\":null,\"ViewId\":\"00000000-0000-0000-0000-000000000000\",\"AvailableOffline\":true,\"MenuId\":null,\"QueryApi\":null,\"Label\":{\"LocalizedLabels\":[],\"UserLocalizedLabel\":null}},\"CascadeConfiguration\":{\"Assign\":\"NoCascade\",\"Delete\":\"NoCascade\",\"Archive\":\"RemoveLink\",\"Merge\":\"NoCascade\",\"Reparent\":\"NoCascade\",\"Share\":\"NoCascade\",\"Unshare\":\"NoCascade\",\"RollupView\":\"NoCascade\"},\"RelationshipAttributes\":[]},{\"MetadataId\":\"95347477-98b4-ef11-a72f-6045bd0a486c\",\"HasChanged\":null,\"IsCustomRelationship\":true,\"IsValidForAdvancedFind\":true,\"SchemaName\":\"mserp_FK_EntAssetMaintenanceAssetServiceLevelV2Entity_FunctionalLocation\",\"SecurityTypes\":\"Append\",\"IsManaged\":true,\"RelationshipType\":\"OneToManyRelationship\",\"IntroducedVersion\":\"1.0.0.0\",\"ReferencedAttribute\":\"mserp_entassetmaintenancefunctionallocationentityid\",\"ReferencedEntity\":\"mserp_entassetmaintenancefunctionallocationentity\",\"ReferencingAttribute\":\"mserp_fk_functionallocation_id\",\"ReferencingEntity\":\"mserp_entassetmaintenanceassetservicelevelv2entity\",\"IsHierarchical\":false,\"EntityKey\":null,\"IsRelationshipAttributeDenormalized\":false,\"ReferencedEntityNavigationPropertyName\":\"mserp_FK_EntAssetMaintenanceAssetServiceLevelV2Entity_FunctionalLocation\",\"ReferencingEntityNavigationPropertyName\":\"mserp_FK_FunctionalLocation_id\",\"RelationshipBehavior\":1,\"IsDenormalizedLookup\":null,\"DenormalizedAttributeName\":null,\"IsCustomizable\":{\"Value\":true,\"CanBeChanged\":false,\"ManagedPropertyLogicalName\":\"iscustomizable\"},\"AssociatedMenuConfiguration\":{\"Behavior\":\"UseCollectionName\",\"Group\":\"Details\",\"Order\":10000,\"IsCustomizable\":true,\"Icon\":null,\"ViewId\":\"00000000-0000-0000-0000-000000000000\",\"AvailableOffline\":true,\"MenuId\":null,\"QueryApi\":null,\"Label\":{\"LocalizedLabels\":[],\"UserLocalizedLabel\":null}},\"CascadeConfiguration\":{\"Assign\":\"NoCascade\",\"Delete\":\"NoCascade\",\"Archive\":\"RemoveLink\",\"Merge\":\"NoCascade\",\"Reparent\":\"NoCascade\",\"Share\":\"NoCascade\",\"Unshare\":\"NoCascade\",\"RollupView\":\"NoCascade\"},\"RelationshipAttributes\":[]},{\"MetadataId\":\"3e379488-9ab4-ef11-a72f-6045bd0a486c\",\"HasChanged\":null,\"IsCustomRelationship\":true,\"IsValidForAdvancedFind\":true,\"SchemaName\":\"mserp_FK_EntAssetMaintenanceAssetServiceLevelV2Entity_WorkOrderType\",\"SecurityTypes\":\"Append\",\"IsManaged\":true,\"RelationshipType\":\"OneToManyRelationship\",\"IntroducedVersion\":\"1.0.0.0\",\"ReferencedAttribute\":\"mserp_entassetmaintenanceworkordertypeentityid\",\"ReferencedEntity\":\"mserp_entassetmaintenanceworkordertypeentity\",\"ReferencingAttribute\":\"mserp_fk_workordertype_id\",\"ReferencingEntity\":\"mserp_entassetmaintenanceassetservicelevelv2entity\",\"IsHierarchical\":false,\"EntityKey\":null,\"IsRelationshipAttributeDenormalized\":false,\"ReferencedEntityNavigationPropertyName\":\"mserp_FK_EntAssetMaintenanceAssetServiceLevelV2Entity_WorkOrderType\",\"ReferencingEntityNavigationPropertyName\":\"mserp_FK_WorkOrderType_id\",\"RelationshipBehavior\":1,\"IsDenormalizedLookup\":null,\"DenormalizedAttributeName\":null,\"IsCustomizable\":{\"Value\":true,\"CanBeChanged\":false,\"ManagedPropertyLogicalName\":\"iscustomizable\"},\"AssociatedMenuConfiguration\":{\"Behavior\":\"UseCollectionName\",\"Group\":\"Details\",\"Order\":10000,\"IsCustomizable\":true,\"Icon\":null,\"ViewId\":\"00000000-0000-0000-0000-000000000000\",\"AvailableOffline\":true,\"MenuId\":null,\"QueryApi\":null,\"Label\":{\"LocalizedLabels\":[],\"UserLocalizedLabel\":null}},\"CascadeConfiguration\":{\"Assign\":\"NoCascade\",\"Delete\":\"NoCascade\",\"Archive\":\"RemoveLink\",\"Merge\":\"NoCascade\",\"Reparent\":\"NoCascade\",\"Share\":\"NoCascade\",\"Unshare\":\"NoCascade\",\"RollupView\":\"NoCascade\"},\"RelationshipAttributes\":[]}],\"OneToManyRelationships\":[],\"ManyToManyRelationships\":[]}",
    "EntityNameOptionSetAttribute": "{\"@odata.context\":\"https://aurorabapenv7cf94.crm10.dynamics.com/api/data/v9.0/$metadata#EntityDefinitions('mserp_entassetmaintenanceassetservicelevelv2entity')/Attributes/Microsoft.Dynamics.CRM.EntityNameAttributeMetadata(MetadataId,LogicalName,SchemaName,DisplayName,OptionSet())\",\"value\":[]}",
    "Forms": "{\"@odata.context\":\"https://aurorabapenv7cf94.crm10.dynamics.com/api/data/v9.0/$metadata#systemforms(name,formid)\",\"value\":[{\"@odata.etag\":\"W/\\\"6827456\\\"\",\"objecttypecode\":\"mserp_entassetmaintenanceassetservicelevelv2entity\",\"formid\":\"d1a92b4d-1c6b-a2b0-b75b-0b378f2ebdd9\",\"name\":\"Information\",\"type\":11},{\"@odata.etag\":\"W/\\\"6827410\\\"\",\"objecttypecode\":\"mserp_entassetmaintenanceassetservicelevelv2entity\",\"formid\":\"969c4550-5cfd-b37e-1600-2e20b691a5d3\",\"name\":\"Information\",\"type\":2},{\"@odata.etag\":\"W/\\\"6827481\\\"\",\"objecttypecode\":\"mserp_entassetmaintenanceassetservicelevelv2entity\",\"formid\":\"73125e38-9fa5-81ca-708b-834d82849cc4\",\"name\":\"Information\",\"type\":6}]}",
    "IconUrl": "",
    "MultiSelectPicklistOptionSetAttribute": "{\"@odata.context\":\"https://aurorabapenv7cf94.crm10.dynamics.com/api/data/v9.0/$metadata#EntityDefinitions('mserp_entassetmaintenanceassetservicelevelv2entity')/Attributes/Microsoft.Dynamics.CRM.MultiSelectPicklistAttributeMetadata(MetadataId,LogicalName,SchemaName,DisplayName,OptionSet())\",\"value\":[]}",
    "PicklistOptionSetAttribute": "{\"@odata.context\":\"https://aurorabapenv7cf94.crm10.dynamics.com/api/data/v9.0/$metadata#EntityDefinitions('mserp_entassetmaintenanceassetservicelevelv2entity')/Attributes/Microsoft.Dynamics.CRM.PicklistAttributeMetadata(MetadataId,LogicalName,SchemaName,DisplayName,OptionSet())\",\"value\":[]}",
    "StateOptionSetAttribute": "{\"@odata.context\":\"https://aurorabapenv7cf94.crm10.dynamics.com/api/data/v9.0/$metadata#EntityDefinitions('mserp_entassetmaintenanceassetservicelevelv2entity')/Attributes/Microsoft.Dynamics.CRM.StateAttributeMetadata(MetadataId,LogicalName,SchemaName,DisplayName,OptionSet())\",\"value\":[]}",
    "StatusOptionSetAttribute": "{\"@odata.context\":\"https://aurorabapenv7cf94.crm10.dynamics.com/api/data/v9.0/$metadata#EntityDefinitions('mserp_entassetmaintenanceassetservicelevelv2entity')/Attributes/Microsoft.Dynamics.CRM.StatusAttributeMetadata(MetadataId,LogicalName,SchemaName,DisplayName,OptionSet())\",\"value\":[]}",
    "TableName": "mserp_entassetmaintenanceassetservicelevelv2entity",
    "Views": "{\"@odata.context\":\"https://aurorabapenv7cf94.crm10.dynamics.com/api/data/v9.0/$metadata#savedqueries(savedqueryid,name,querytype)\",\"value\":[{\"@odata.etag\":\"W/\\\"6827515\\\"\",\"savedqueryid\":\"d72dd79b-9b7a-23a0-b71b-062897ae25d7\",\"name\":\"Asset management maintenance service levels V2 (mserp) Advanced Find View\",\"querytype\":1},{\"@odata.etag\":\"W/\\\"6827491\\\"\",\"savedqueryid\":\"9c58e444-f659-1797-3cb2-759aabf6fc01\",\"name\":\"Asset management maintenance service levels V2 (mserp) Associated View\",\"querytype\":2},{\"@odata.etag\":\"W/\\\"6827503\\\"\",\"savedqueryid\":\"df7777df-0bf4-5c13-a3b0-d58e3402d086\",\"name\":\"Asset management maintenance service levels V2 (mserp) Lookup View\",\"querytype\":64},{\"@odata.etag\":\"W/\\\"6827540\\\"\",\"savedqueryid\":\"d5ef1b84-d0f0-b530-2d1a-e728010ab987\",\"name\":\"All Asset management maintenance service levels V2 (mserp)\",\"querytype\":0}]}"
  },
  "UnusedDataSources": {},
  "webApiVersion": "v9.0"
}